[
  {"map": "unmei",   "x":   2,  "y":  5, "chara": "cordelia",  "atr": null, "zoen": null},
  {"map": "unmei",   "x":   2,  "y":  5, "chara": "lissa",     "atr": "b",  "zoen": null},
  {"map": "unmei",   "x":   2,  "y":  7, "chara": "validar",   "atr": "b",  "zoen": null},
  {"map": "unmei",   "x":   3,  "y":  6, "chara": "frederick", "atr": null, "zoen": null},
  {"map": "unmei",   "x":   3,  "y":  6, "chara": "cordelia",  "atr": "b",  "zoen": null},
  {"map": "unmei",   "x":   4,  "y":  2, "chara": "robin",     "atr": "s",  "zoen": null},
  {"map": "unmei",   "x":   4,  "y":  2, "chara": "robin",     "atr": "s",  "zoen": null},
  {"map": "unmei",   "x":   4,  "y":  2, "chara": "robin",     "atr": "b",  "zoen": null},
  {"map": "unmei",   "x":   5,  "y":  2, "chara": "lianna",    "atr": null, "zoen": null},
  {"map": "unmei",   "x":   5,  "y":  2, "chara": "chrom",     "atr": "b",  "zoen": null},
  {"map": "unmei",   "x":   6,  "y":  3, "chara": "cordelia",  "atr": null, "zoen": null},
  {"map": "unmei",   "x":   6,  "y":  3, "chara": "validar",   "atr": "b",  "zoen": null},
  {"map": "unmei",   "x":   6,  "y":  8, "chara": "tiki",      "atr": null, "zoen": null},
  {"map": "unmei",   "x":   6,  "y":  8, "chara": "cordelia",  "atr": null, "zoen": null},
  {"map": "unmei",   "x":   6,  "y":  8, "chara": "lianna",    "atr": null, "zoen": null},
  {"map": "unmei",   "x":   6,  "y":  8, "chara": "robin",     "atr": "b",  "zoen": null},
  {"map": "unmei",   "x":   9,  "y":  3, "chara": "robin",     "atr": null, "zoen": null},
  {"map": "unmei",   "x":   9,  "y":  3, "chara": "validar",   "atr": "b",  "zoen": null},
  {"map": "unmei",   "x":   9,  "y":  6, "chara": "ceada",     "atr": null, "zoen": null},
  {"map": "unmei",   "x":   9,  "y":  6, "chara": "robin",     "atr": "b",  "zoen": null},
  {"map": "unmei",   "x":   11, "y":  5, "chara": "cordelia",  "atr": null, "zoen": null},
  {"map": "unmei",   "x":   11, "y":  5, "chara": "frederick", "atr": null, "zoen": null},
  {"map": "unmei",   "x":   11, "y":  5, "chara": "lissa",     "atr": "b",  "zoen": null},
  {"map": "unmei",   "x":   12, "y":  9, "chara": "frederick", "atr": null, "zoen": null},
  {"map": "unmei",   "x":   14, "y":  3, "chara": "owain",     "atr": null, "zoen": null},
  {"map": "unmei",   "x":   14, "y":  3, "chara": "robin",     "atr": "b",  "zoen": null},
  {"map": "unmei",   "x":   14, "y":  5, "chara": "frederick", "atr": null, "zoen": null},
  {"map": "unmei",   "x":   14, "y":  5, "chara": "rowan",     "atr": "b",  "zoen": null},
  {"map": "unmei",   "x":   14, "y":  8, "chara": "frederick", "atr": null, "zoen": null},
  {"map": "unmei",   "x":   14, "y":  8, "chara": "lissa",     "atr": null, "zoen": null},
  {"map": "unmei",   "x":   14, "y":  8, "chara": "robin",     "atr": "b",  "zoen": null},
  {"map": "unmei",   "x":   15, "y":  2, "chara": "lianna",    "atr": null, "zoen": null},
  {"map": "unmei",   "x":   15, "y":  2, "chara": "rowan",     "atr": null, "zoen": null},
  {"map": "unmei",   "x":   15, "y":  2, "chara": "frederick", "atr": "b",  "zoen": null},
  {"map": "unmei",   "x":   15, "y":  6, "chara": "cordelia",  "atr": null, "zoen": null},
  {"map": "unmei",   "x":   15, "y":  6, "chara": "rowan",     "atr": null, "zoen": null},
  {"map": "unmei",   "x":   15, "y":  6, "chara": "robin",     "atr": "b",  "zoen": null},
  {"map": "unmei",   "x":   16, "y":  4, "chara": "chrom",     "atr": null, "zoen": null},
  {"map": "unmei",   "x":   16, "y":  4, "chara": "cordelia",  "atr": "b",  "zoen": null},
  {"map": "sonote",  "x":   2,  "y":  2, "chara": "corrin",    "atr": null, "zoen": null},
  {"map": "sonote",  "x":   2,  "y":  5, "chara": "robin",     "atr": null, "zoen": null},
  {"map": "sonote",  "x":   2,  "y":  5, "chara": "niles",     "atr": null, "zoen": null},
  {"map": "sonote",  "x":   2,  "y":  5, "chara": "leo",       "atr": "b",  "zoen": null},
  {"map": "sonote",  "x":   2,  "y":  8, "chara": "rowan",     "atr": null, "zoen": null},
  {"map": "sonote",  "x":   2,  "y":  8, "chara": "chrom",     "atr": null, "zoen": null},
  {"map": "sonote",  "x":   2,  "y":  8, "chara": "corrin",    "atr": "b",  "zoen": null},
  {"map": "sonote",  "x":   3,  "y":  6, "chara": "validar",   "atr": null, "zoen": null},
  {"map": "sonote",  "x":   3,  "y":  6, "chara": "robin",     "atr": "b",  "zoen": null},
  {"map": "sonote",  "x":   4,  "y":  4, "chara": "cordelia",  "atr": null, "zoen": null},
  {"map": "sonote",  "x":   4,  "y":  4, "chara": "lissa",     "atr": "b",  "zoen": null},
  {"map": "sonote",  "x":   5,  "y":  8, "chara": "niles",     "atr": null, "zoen": null},
  {"map": "sonote",  "x":   5,  "y":  8, "chara": "leo",       "atr": null, "zoen": null},
  {"map": "sonote",  "x":   5,  "y":  8, "chara": "camilla",   "atr": null, "zoen": null},
  {"map": "sonote",  "x":   5,  "y":  8, "chara": "elise",     "atr": null, "zoen": null},
  {"map": "sonote",  "x":   5,  "y":  8, "chara": "xander",    "atr": "b",  "zoen": null},
  {"map": "sonote",  "x":   6,  "y":  5, "chara": "corrin",    "atr": null, "zoen": null},
  {"map": "sonote",  "x":   6,  "y":  5, "chara": "camilla",   "atr": "b",  "zoen": null},
  {"map": "sonote",  "x":   7,  "y":  6, "chara": "lucina",    "atr": "b",  "zoen": null},
  {"map": "sonote",  "x":   9,  "y":  3, "chara": "chrom",     "atr": "b",  "zoen": null},
  {"map": "sonote",  "x":   10, "y":  8, "chara": "takumi",    "atr": null, "zoen": null},
  {"map": "sonote",  "x":   10, "y":  8, "chara": "oboro",     "atr": null, "zoen": null},
  {"map": "sonote",  "x":   10, "y":  8, "chara": "hinoka",    "atr": null, "zoen": null},
  {"map": "sonote",  "x":   10, "y":  8, "chara": "sakura",    "atr": null, "zoen": null},
  {"map": "sonote",  "x":   10, "y":  8, "chara": "ryoma",     "atr": "b",  "zoen": null},
  {"map": "sonote",  "x":   12, "y":  5, "chara": "oboro",     "atr": null, "zoen": null},
  {"map": "sonote",  "x":   13, "y":  1, "chara": "lianna",    "atr": "b",  "zoen": null},
  {"map": "sonote",  "x":   13, "y":  3, "chara": "lianna",    "atr": null, "zoen": null},
  {"map": "sonote",  "x":   13, "y":  3, "chara": "cordelia",  "atr": "b",  "zoen": null},
  {"map": "sonote",  "x":   13, "y":  6, "chara": "oboro",     "atr": null, "zoen": null},
  {"map": "sonote",  "x":   13, "y":  6, "chara": "takumi",    "atr": "b",  "zoen": null},
  {"map": "sonote",  "x":   14, "y":  5, "chara": "owain",     "atr": null, "zoen": null},
  {"map": "sonote",  "x":   14, "y":  5, "chara": "lucina",    "atr": null, "zoen": null},
  {"map": "sonote",  "x":   14, "y":  5, "chara": "rowan",     "atr": "b",  "zoen": null},
  {"map": "sonote",  "x":   14, "y":  8, "chara": "cordelia",  "atr": null, "zoen": null},
  {"map": "sonote",  "x":   14, "y":  8, "chara": "sakura",    "atr": null, "zoen": null},
  {"map": "sonote",  "x":   14, "y":  8, "chara": "validar",   "atr": null, "zoen": null},
  {"map": "sonote",  "x":   14, "y":  8, "chara": "hinoka",    "atr": "b",  "zoen": null},
  {"map": "sonote",  "x":   15, "y":  7, "chara": "sakura",    "atr": "b",  "zoen": null},
  {"map": "sonote",  "x":   16, "y":  2, "chara": "elise",     "atr": null, "zoen": null},
  {"map": "sonote",  "x":   16, "y":  2, "chara": "sakura",    "atr": null, "zoen": null},
  {"map": "sonote",  "x":   16, "y":  8, "chara": "sakura",    "atr": null, "zoen": null},
  {"map": "sonote",  "x":   16, "y":  8, "chara": "takumi",    "atr": "b",  "zoen": null},
  {"map": "akuno",   "x":   3,  "y":  3, "chara": "robin",     "atr": null, "zoen": null},
  {"map": "akuno",   "x":   3,  "y":  3, "chara": "rowan",     "atr": null, "zoen": null},
  {"map": "akuno",   "x":   3,  "y":  3, "chara": "gharnef",   "atr": "b",  "zoen": null},
  {"map": "akuno",   "x":   5,  "y":  3, "chara": "cordelia",  "atr": null, "zoen": null},
  {"map": "akuno",   "x":   5,  "y":  3, "chara": "hinoka",    "atr": null, "zoen": null},
  {"map": "akuno",   "x":   5,  "y":  3, "chara": "camilla",   "atr": "b",  "zoen": null},
  {"map": "akuno",   "x":   5,  "y":  4, "chara": "camilla",   "atr": null, "zoen": null},
  {"map": "akuno",   "x":   5,  "y":  4, "chara": "elise",     "atr": "b",  "zoen": null},
  {"map": "akuno",   "x":   5,  "y":  4, "chara": "robin",     "atr": null, "zoen": null},
  {"map": "akuno",   "x":   5,  "y":  4, "chara": "cordelia",  "atr": "b",  "zoen": null},
  {"map": "akuno",   "x":   6,  "y":  5, "chara": "frederick", "atr": null, "zoen": null},
  {"map": "akuno",   "x":   6,  "y":  5, "chara": "robin",     "atr": "b",  "zoen": null},
  {"map": "akuno",   "x":   6,  "y":  5, "chara": "validar",   "atr": null, "zoen": null},
  {"map": "akuno",   "x":   6,  "y":  5, "chara": "gharnef",   "atr": "b",  "zoen": null},
  {"map": "akuno",   "x":   6,  "y":  6, "chara": "ceada",     "atr": null, "zoen": null},
  {"map": "akuno",   "x":   6,  "y":  6, "chara": "marth",     "atr": "b",  "zoen": null},
  {"map": "akuno",   "x":   7,  "y":  8, "chara": "ryoma",     "atr": null, "zoen": null},
  {"map": "akuno",   "x":   7,  "y":  8, "chara": "tiki",      "atr": "b",  "zoen": null},
  {"map": "akuno",   "x":   8,  "y":  5, "chara": "lissa",     "atr": null, "zoen": null},
  {"map": "akuno",   "x":   8,  "y":  5, "chara": "lucina",    "atr": null, "zoen": null},
  {"map": "akuno",   "x":   8,  "y":  5, "chara": "sakura",    "atr": "b",  "zoen": null},
  {"map": "akuno",   "x":   8,  "y":  7, "chara": "lissa",     "atr": null, "zoen": null},
  {"map": "akuno",   "x":   8,  "y":  7, "chara": "camilla",   "atr": "b",  "zoen": null},
  {"map": "akuno",   "x":   8,  "y":  7, "chara": "ceada",     "atr": null, "zoen": null},
  {"map": "akuno",   "x":   8,  "y":  7, "chara": "elise",     "atr": "b",  "zoen": null},
  {"map": "akuno",   "x":   8,  "y":  9, "chara": "validar",   "atr": null, "zoen": null},
  {"map": "akuno",   "x":   8,  "y":  9, "chara": "gharnef",   "atr": "b",  "zoen": null},
  {"map": "akuno",   "x":   10, "y":  4, "chara": "frederick", "atr": null, "zoen": null},
  {"map": "akuno",   "x":   10, "y":  4, "chara": "robin",     "atr": null, "zoen": null},
  {"map": "akuno",   "x":   10, "y":  4, "chara": "rowan",     "atr": "b",  "zoen": null},
  {"map": "akuno",   "x":   10, "y":  8, "chara": "ryoma",     "atr": "s",  "zoen": null},
  {"map": "akuno",   "x":   10, "y":  8, "chara": "ryoma",     "atr": "b",  "zoen": null},
  {"map": "akuno",   "x":   10, "y":  8, "chara": "gharnef",   "atr": "b",  "zoen": null},
  {"map": "akuno",   "x":   11, "y":  7, "chara": "elise",     "atr": null, "zoen": null},
  {"map": "akuno",   "x":   12, "y":  3, "chara": "leo",       "atr": null, "zoen": null},
  {"map": "akuno",   "x":   12, "y":  3, "chara": "elise",     "atr": "b",  "zoen": null},
  {"map": "akuno",   "x":   12, "y":  3, "chara": "corrin",    "atr": null, "zoen": null},
  {"map": "akuno",   "x":   12, "y":  3, "chara": "ryoma",     "atr": "b",  "zoen": null},
  {"map": "akuno",   "x":   13, "y":  2, "chara": "corrin",    "atr": null, "zoen": null},
  {"map": "akuno",   "x":   13, "y":  2, "chara": "xander",    "atr": "b",  "zoen": null},
  {"map": "akuno",   "x":   13, "y":  5, "chara": "rowan",     "atr": null, "zoen": null},
  {"map": "akuno",   "x":   13, "y":  5, "chara": "frederick", "atr": "b",  "zoen": null},
  {"map": "akuno",   "x":   13, "y":  7, "chara": "corrin",    "atr": null, "zoen": null},
  {"map": "akuno",   "x":   13, "y":  7, "chara": "oboro",     "atr": "b",  "zoen": null},
  {"map": "akuno",   "x":   13, "y":  7, "chara": "cordelia",  "atr": null, "zoen": null},
  {"map": "akuno",   "x":   13, "y":  7, "chara": "owain",     "atr": "b",  "zoen": null},
  {"map": "akuno",   "x":   15, "y":  1, "chara": "corrin",    "atr": null, "zoen": null},
  {"map": "akuno",   "x":   15, "y":  1, "chara": "camilla",   "atr": "b",  "zoen": null},
  {"map": "akuno",   "x":   17, "y":  2, "chara": "robin",     "atr": null, "zoen": null},
  {"map": "kiaran",  "x":   1,  "y":  4, "chara": "lissa",     "atr": null, "zoen": null},
  {"map": "kiaran",  "x":   1,  "y":  4, "chara": "corrin",    "atr": null, "zoen": null},
  {"map": "kiaran",  "x":   1,  "y":  4, "chara": "elise",     "atr": "b",  "zoen": null},
  {"map": "kiaran",  "x":   3,  "y":  3, "chara": "chrom",     "atr": "b",  "zoen": null},
  {"map": "kiaran",  "x":   3,  "y":  6, "chara": "camilla",   "atr": null, "zoen": null},
  {"map": "kiaran",  "x":   3,  "y":  6, "chara": "cordelia",  "atr": "b",  "zoen": null},
  {"map": "kiaran",  "x":   3,  "y":  6, "chara": "oboro",     "atr": null, "zoen": null},
  {"map": "kiaran",  "x":   3,  "y":  6, "chara": "hinoka",    "atr": "b",  "zoen": null},
  {"map": "kiaran",  "x":   4,  "y":  4, "chara": "lissa",     "atr": null, "zoen": null},
  {"map": "kiaran",  "x":   4,  "y":  4, "chara": "owain",     "atr": null, "zoen": null},
  {"map": "kiaran",  "x":   4,  "y":  4, "chara": "chrom",     "atr": "b",  "zoen": null},
  {"map": "kiaran",  "x":   4,  "y":  8, "chara": "lissa",     "atr": "b",  "zoen": null},
  {"map": "kiaran",  "x":   5,  "y":  1, "chara": "marth",     "atr": "b",  "zoen": null},
  {"map": "kiaran",  "x":   5,  "y":  1, "chara": "xander",    "atr": "b",  "zoen": null},
  {"map": "kiaran",  "x":   5,  "y":  5, "chara": "frederick", "atr": null, "zoen": null},
  {"map": "kiaran",  "x":   5,  "y":  5, "chara": "camilla",   "atr": "b",  "zoen": null},
  {"map": "kiaran",  "x":   5,  "y":  5, "chara": "cordelia",  "atr": null, "zoen": null},
  {"map": "kiaran",  "x":   5,  "y":  5, "chara": "ceada",     "atr": "b",  "zoen": null},
  {"map": "kiaran",  "x":   6,  "y":  3, "chara": "validar",   "atr": "b",  "zoen": null},
  {"map": "kiaran",  "x":   6,  "y":  6, "chara": "rowan",     "atr": "b",  "zoen": null},
  {"map": "kiaran",  "x":   9,  "y":  3, "chara": "oboro",     "atr": null, "zoen": null},
  {"map": "kiaran",  "x":   9,  "y":  3, "chara": "hinoka",    "atr": "b",  "zoen": null},
  {"map": "kiaran",  "x":   9,  "y":  9, "chara": "gharnef",   "atr": null, "zoen": null},
  {"map": "kiaran",  "x":   10, "y":  1, "chara": "elise",     "atr": null, "zoen": null},
  {"map": "kiaran",  "x":   10, "y":  1, "chara": "cordelia",  "atr": null, "zoen": null},
  {"map": "kiaran",  "x":   10, "y":  1, "chara": "camilla",   "atr": "b",  "zoen": null},
  {"map": "kiaran",  "x":   12, "y":  2, "chara": "corrin",    "atr": null, "zoen": null},
  {"map": "kiaran",  "x":   12, "y":  2, "chara": "hinoka",    "atr": null, "zoen": null},
  {"map": "kiaran",  "x":   12, "y":  2, "chara": "takumi",    "atr": null, "zoen": null},
  {"map": "kiaran",  "x":   12, "y":  2, "chara": "ryoma",     "atr": "b",  "zoen": null},
  {"map": "kiaran",  "x":   12, "y":  3, "chara": "lianna",    "atr": null, "zoen": null},
  {"map": "kiaran",  "x":   12, "y":  3, "chara": "lucina",    "atr": "b",  "zoen": null},
  {"map": "kiaran",  "x":   12, "y":  3, "chara": "cordelia",  "atr": null, "zoen": null},
  {"map": "kiaran",  "x":   12, "y":  3, "chara": "marth",     "atr": "b",  "zoen": null},
  {"map": "kiaran",  "x":   14, "y":  9, "chara": "xander",    "atr": null, "zoen": null},
  {"map": "kiaran",  "x":   14, "y":  9, "chara": "rowan",     "atr": "b",  "zoen": null},
  {"map": "kiaran",  "x":   14, "y":  9, "chara": "frederick", "atr": null, "zoen": null},
  {"map": "kiaran",  "x":   14, "y":  9, "chara": "chrom",     "atr": "b",  "zoen": null},
  {"map": "kiaran",  "x":   15, "y":  3, "chara": "validar",   "atr": "b",  "zoen": null},
  {"map": "kiaran",  "x":   15, "y":  5, "chara": "hinoka",    "atr": "b",  "zoen": null},
  {"map": "kiaran",  "x":   16, "y":  6, "chara": "marth",     "atr": null, "zoen": null},
  {"map": "kiaran",  "x":   16, "y":  6, "chara": "ceada",     "atr": null, "zoen": null},
  {"map": "kiaran",  "x":   16, "y":  6, "chara": "tiki",      "atr": "b",  "zoen": null},
  {"map": "kiaran",  "x":   16, "y":  8, "chara": "takumi",    "atr": null, "zoen": null},
  {"map": "kiaran",  "x":   16, "y":  8, "chara": "lyn",       "atr": null, "zoen": null},
  {"map": "kiaran",  "x":   16, "y":  8, "chara": "takumi",    "atr": "s",  "zoen": null},
  {"map": "kiaran",  "x":   16, "y":  8, "chara": "robin",     "atr": null, "zoen": null},
  {"map": "kiaran",  "x":   16, "y":  8, "chara": "iago",      "atr": "b",  "zoen": null},
  {"map": "kiaran",  "x":   17, "y":  6, "chara": "xander",    "atr": "b",  "zoen": null},
  {"map": "saikai",  "x":   2,  "y":  2, "chara": "corrin",    "atr": null, "zoen": null},
  {"map": "saikai",  "x":   2,  "y":  8, "chara": "darios",    "atr": "b",  "zoen": null},
  {"map": "saikai",  "x":   3,  "y":  5, "chara": "ceada",     "atr": null, "zoen": null},
  {"map": "saikai",  "x":   3,  "y":  5, "chara": "tiki",      "atr": null, "zoen": null},
  {"map": "saikai",  "x":   3,  "y":  5, "chara": "chrom",     "atr": null, "zoen": null},
  {"map": "saikai",  "x":   3,  "y":  5, "chara": "darios",    "atr": "b",  "zoen": null},
  {"map": "saikai",  "x":   4,  "y":  3, "chara": "leo",       "atr": "b",  "zoen": null},
  {"map": "saikai",  "x":   4,  "y":  3, "chara": "ryoma",     "atr": "b",  "zoen": null},
  {"map": "saikai",  "x":   4,  "y":  9, "chara": "sakura",    "atr": null, "zoen": null},
  {"map": "saikai",  "x":   4,  "y":  9, "chara": "tiki",      "atr": "b",  "zoen": null},
  {"map": "saikai",  "x":   4,  "y":  9, "chara": "camilla",   "atr": null, "zoen": null},
  {"map": "saikai",  "x":   4,  "y":  9, "chara": "lissa",     "atr": "b",  "zoen": null},
  {"map": "saikai",  "x":   5,  "y":  4, "chara": "robin",     "atr": "b",  "zoen": null},
  {"map": "saikai",  "x":   5,  "y":  9, "chara": "marth",     "atr": null, "zoen": null},
  {"map": "saikai",  "x":   5,  "y":  9, "chara": "tiki",      "atr": "b",  "zoen": null},
  {"map": "saikai",  "x":   7,  "y":  5, "chara": "ceada",     "atr": "b",  "zoen": null},
  {"map": "saikai",  "x":   7,  "y":  8, "chara": "iago",      "atr": "b",  "zoen": null},
  {"map": "saikai",  "x":   9,  "y":  3, "chara": "validar",   "atr": null, "zoen": null},
  {"map": "saikai",  "x":   9,  "y":  3, "chara": "darios",    "atr": null, "zoen": null},
  {"map": "saikai",  "x":   9,  "y":  3, "chara": "takumi",    "atr": null, "zoen": null},
  {"map": "saikai",  "x":   9,  "y":  3, "chara": "iago",      "atr": null, "zoen": null},
  {"map": "saikai",  "x":   9,  "y":  3, "chara": "gharnef",   "atr": "b",  "zoen": null},
  {"map": "saikai",  "x":   9,  "y":  6, "chara": "niles",     "atr": "s",  "zoen": null},
  {"map": "saikai",  "x":   9,  "y":  6, "chara": "niles",     "atr": "b",  "zoen": null},
  {"map": "saikai",  "x":   9,  "y":  6, "chara": "takumi",    "atr": "s",  "zoen": null},
  {"map": "saikai",  "x":   9,  "y":  6, "chara": "takumi",    "atr": "b",  "zoen": null},
  {"map": "saikai",  "x":   11, "y":  7, "chara": "elise",     "atr": null, "zoen": null},
  {"map": "saikai",  "x":   11, "y":  7, "chara": "tiki",      "atr": null, "zoen": null},
  {"map": "saikai",  "x":   11, "y":  7, "chara": "camilla",   "atr": null, "zoen": null},
  {"map": "saikai",  "x":   11, "y":  7, "chara": "celica",    "atr": "b",  "zoen": null},
  {"map": "saikai",  "x":   13, "y":  5, "chara": "tiki",      "atr": "b",  "zoen": null},
  {"map": "saikai",  "x":   13, "y":  6, "chara": "frederick", "atr": null, "zoen": null},
  {"map": "saikai",  "x":   13, "y":  6, "chara": "validar",   "atr": "b",  "zoen": null},
  {"map": "saikai",  "x":   13, "y":  8, "chara": "frederick", "atr": null, "zoen": null},
  {"map": "saikai",  "x":   13, "y":  8, "chara": "elise",     "atr": null, "zoen": null},
  {"map": "saikai",  "x":   13, "y":  8, "chara": "lissa",     "atr": null, "zoen": null},
  {"map": "saikai",  "x":   13, "y":  8, "chara": "ryoma",     "atr": "b",  "zoen": null},
  {"map": "saikai",  "x":   14, "y":  4, "chara": "camilla",   "atr": null, "zoen": null},
  {"map": "saikai",  "x":   14, "y":  4, "chara": "tiki",      "atr": null, "zoen": null},
  {"map": "saikai",  "x":   14, "y":  4, "chara": "marth",     "atr": null, "zoen": null},
  {"map": "saikai",  "x":   14, "y":  4, "chara": "corrin",    "atr": "b",  "zoen": null},
  {"map": "saikai",  "x":   15, "y":  2, "chara": "iago",      "atr": null, "zoen": null},
  {"map": "saikai",  "x":   15, "y":  2, "chara": "xander",    "atr": null, "zoen": null},
  {"map": "saikai",  "x":   15, "y":  2, "chara": "validar",   "atr": null, "zoen": null},
  {"map": "saikai",  "x":   15, "y":  2, "chara": "camilla",   "atr": null, "zoen": null},
  {"map": "saikai",  "x":   15, "y":  2, "chara": "darios",    "atr": "b",  "zoen": null},
  {"map": "saikai",  "x":   15, "y":  5, "chara": "hinoka",    "atr": null, "zoen": null},
  {"map": "saikai",  "x":   15, "y":  5, "chara": "sakura",    "atr": null, "zoen": null},
  {"map": "saikai",  "x":   15, "y":  5, "chara": "takumi",    "atr": "b",  "zoen": null},
  {"map": "saikai",  "x":   16, "y":  5, "chara": "lissa",     "atr": null, "zoen": null},
  {"map": "saikai",  "x":   16, "y":  5, "chara": "elise",     "atr": null, "zoen": null},
  {"map": "saikai",  "x":   16, "y":  5, "chara": "lucina",    "atr": "b",  "zoen": null},
  {"map": "eiyuu",   "x":   3,  "y":  6, "chara": "rowan",     "atr": "s",  "zoen": null},
  {"map": "eiyuu",   "x":   3,  "y":  6, "chara": "darios",    "atr": "b",  "zoen": null},
  {"map": "eiyuu",   "x":   3,  "y":  6, "chara": "lianna",    "atr": null, "zoen": null},
  {"map": "eiyuu",   "x":   3,  "y":  6, "chara": "celica",    "atr": "b",  "zoen": null},
  {"map": "eiyuu",   "x":   6,  "y":  2, "chara": "navarre",   "atr": null, "zoen": null},
  {"map": "eiyuu",   "x":   6,  "y":  2, "chara": "tiki",      "atr": null, "zoen": null},
  {"map": "eiyuu",   "x":   6,  "y":  2, "chara": "ceada",     "atr": null, "zoen": null},
  {"map": "eiyuu",   "x":   6,  "y":  2, "chara": "marth",     "atr": "b",  "zoen": null},
  {"map": "eiyuu",   "x":   15, "y":  6, "chara": "lianna",    "atr": null, "zoen": null},
  {"map": "eiyuu",   "x":   15, "y":  6, "chara": "rowan",     "atr": null, "zoen": null},
  {"map": "eiyuu",   "x":   15, "y":  6, "chara": "darios",    "atr": null, "zoen": null},
  {"map": "eiyuu",   "x":   15, "y":  6, "chara": "lyn",       "atr": "b",  "zoen": null},
  {"map": "nageki",  "x":   1,  "y":  4, "chara": "darios",    "atr": "b",  "zoen": null},
  {"map": "nageki",  "x":   3,  "y":  7, "chara": "camilla",   "atr": "b",  "zoen": null},
  {"map": "nageki",  "x":   5,  "y":  6, "chara": "sakura",    "atr": "b",  "zoen": null},
  {"map": "nageki",  "x":   7,  "y":  9, "chara": "camilla",   "atr": null, "zoen": null},
  {"map": "nageki",  "x":   7,  "y":  9, "chara": "lissa",     "atr": null, "zoen": null},
  {"map": "nageki",  "x":   7,  "y":  9, "chara": "tiki",      "atr": "b",  "zoen": null},
  {"map": "nageki",  "x":   9,  "y":  9, "chara": "corrin",    "atr": "b",  "zoen": null},
  {"map": "nageki",  "x":   10, "y":  4, "chara": "cordelia",  "atr": null, "zoen": null},
  {"map": "nageki",  "x":   10, "y":  4, "chara": "frederick", "atr": null, "zoen": null},
  {"map": "nageki",  "x":   10, "y":  4, "chara": "lissa",     "atr": "b",  "zoen": null},
  {"map": "nageki",  "x":   10, "y":  9, "chara": "tiki",      "atr": null, "zoen": null},
  {"map": "nageki",  "x":   10, "y":  9, "chara": "owain",     "atr": "b",  "zoen": null},
  {"map": "nageki",  "x":   10, "y":  9, "chara": "rowan",     "atr": null, "zoen": null},
  {"map": "nageki",  "x":   10, "y":  9, "chara": "anna",      "atr": "b",  "zoen": null},
  {"map": "nageki",  "x":   11, "y":  3, "chara": "iago",      "atr": "b",  "zoen": null},
  {"map": "nageki",  "x":   11, "y":  8, "chara": "frederick", "atr": null, "zoen": null},
  {"map": "nageki",  "x":   12, "y":  9, "chara": "lianna",    "atr": null, "zoen": null},
  {"map": "nageki",  "x":   12, "y":  9, "chara": "corrin",    "atr": null, "zoen": null},
  {"map": "nageki",  "x":   12, "y":  9, "chara": "camilla",   "atr": null, "zoen": null},
  {"map": "nageki",  "x":   12, "y":  9, "chara": "hinoka",    "atr": "b",  "zoen": null},
  {"map": "nageki",  "x":   15, "y":  5, "chara": "oboro",     "atr": null, "zoen": null},
  {"map": "nageki",  "x":   15, "y":  5, "chara": "lyn",       "atr": null, "zoen": null},
  {"map": "nageki",  "x":   15, "y":  5, "chara": "frederick", "atr": "b",  "zoen": null},
  {"map": "nageki",  "x":   16, "y":  2, "chara": "sakura",    "atr": null, "zoen": null},
  {"map": "nageki",  "x":   16, "y":  2, "chara": "takumi",    "atr": null, "zoen": null},
  {"map": "nageki",  "x":   16, "y":  2, "chara": "camilla",   "atr": null, "zoen": null},
  {"map": "nageki",  "x":   16, "y":  2, "chara": "corrin",    "atr": "b",  "zoen": null},
  {"map": "nageki",  "x":   16, "y":  3, "chara": "marth",     "atr": "b",  "zoen": null},
  {"map": "nageki",  "x":   17, "y":  4, "chara": "ceada",     "atr": "b",  "zoen": null},
  {"map": "nageki",  "x":   17, "y":  7, "chara": "gharnef",   "atr": "b",  "zoen": null},
  {"map": "kamigami","x":   2,  "y":  1, "chara": "gharnef",   "atr": null, "zoen": null},
  {"map": "kamigami","x":   2,  "y":  1, "chara": "rowan",     "atr": null, "zoen": null},
  {"map": "kamigami","x":   2,  "y":  1, "chara": "sakura",    "atr": "b",  "zoen": null},
  {"map": "kamigami","x":   5,  "y":  9, "chara": "navarre",   "atr": "b",  "zoen": null},
  {"map": "kamigami","x":   6,  "y":  5, "chara": "ceada",     "atr": "b",  "zoen": null},
  {"map": "kamigami","x":   7,  "y":  6, "chara": "robin",     "atr": "b",  "zoen": null},
  {"map": "kamigami","x":   10, "y":  6, "chara": "frederick", "atr": null, "zoen": null},
  {"map": "kamigami","x":   10, "y":  6, "chara": "lissa",     "atr": "b",  "zoen": null},
  {"map": "kamigami","x":   10, "y":  6, "chara": "oboro",     "atr": null, "zoen": null},
  {"map": "kamigami","x":   10, "y":  6, "chara": "anna",      "atr": "b",  "zoen": null},
  {"map": "kamigami","x":   11, "y":  5, "chara": "elise",     "atr": "b",  "zoen": null},
  {"map": "kamigami","x":   12, "y":  4, "chara": "frederick", "atr": "b",  "zoen": null},
  {"map": "kamigami","x":   13, "y":  3, "chara": "owain",     "atr": "b",  "zoen": null},
  {"map": "kamigami","x":   13, "y":  5, "chara": "lucina",    "atr": null, "zoen": null},
  {"map": "kamigami","x":   13, "y":  5, "chara": "cordelia",  "atr": null, "zoen": null},
  {"map": "kamigami","x":   13, "y":  5, "chara": "tiki",      "atr": null, "zoen": null},
  {"map": "kamigami","x":   13, "y":  5, "chara": "lyn",       "atr": "b",  "zoen": null},
  {"map": "kamigami","x":   13, "y":  8, "chara": "marth",     "atr": "s",  "zoen": null},
  {"map": "kamigami","x":   15, "y":  9, "chara": "celica",    "atr": null, "zoen": null},
  {"map": "kamigami","x":   15, "y":  9, "chara": "cordelia",  "atr": null, "zoen": null},
  {"map": "kamigami","x":   15, "y":  9, "chara": "tiki",      "atr": "b",  "zoen": null},
  {"map": "kamigami","x":   17, "y":  2, "chara": "camilla",   "atr": null, "zoen": null},
  {"map": "kamigami","x":   17, "y":  2, "chara": "corrin",    "atr": null, "zoen": null},
  {"map": "kamigami","x":   17, "y":  2, "chara": "azura",     "atr": "b",  "zoen": null},
  {"map": "koori",   "x":   1,  "y":  1, "chara": "azura",     "atr": null, "zoen": null},
  {"map": "koori",   "x":   1,  "y":  1, "chara": "takumi",    "atr": null, "zoen": null},
  {"map": "koori",   "x":   1,  "y":  1, "chara": "sakura",    "atr": null, "zoen": null},
  {"map": "koori",   "x":   1,  "y":  1, "chara": "ryoma",     "atr": "b",  "zoen": null},
  {"map": "koori",   "x":   3,  "y":  4, "chara": "leo",       "atr": null, "zoen": null},
  {"map": "koori",   "x":   3,  "y":  4, "chara": "camilla",   "atr": "b",  "zoen": null},
  {"map": "koori",   "x":   4,  "y":  7, "chara": "lyn",       "atr": "b",  "zoen": null},
  {"map": "koori",   "x":   4,  "y":  9, "chara": "xander",    "atr": null, "zoen": null},
  {"map": "koori",   "x":   4,  "y":  9, "chara": "azura",     "atr": "b",  "zoen": null},
  {"map": "koori",   "x":   4,  "y":  9, "chara": "robin",     "atr": null, "zoen": null},
  {"map": "koori",   "x":   4,  "y":  9, "chara": "cordelia",  "atr": "b",  "zoen": null},
  {"map": "koori",   "x":   5,  "y":  8, "chara": "robin",     "atr": "b",  "zoen": null},
  {"map": "koori",   "x":   7,  "y":  5, "chara": "marth",     "atr": null, "zoen": null},
  {"map": "koori",   "x":   7,  "y":  5, "chara": "frederick", "atr": null, "zoen": null},
  {"map": "koori",   "x":   7,  "y":  5, "chara": "tiki",      "atr": null, "zoen": null},
  {"map": "koori",   "x":   7,  "y":  5, "chara": "chrom",     "atr": "b",  "zoen": null},
  {"map": "koori",   "x":   8,  "y":  3, "chara": "takumi",    "atr": null, "zoen": null},
  {"map": "koori",   "x":   8,  "y":  3, "chara": "frederick", "atr": null, "zoen": null},
  {"map": "koori",   "x":   8,  "y":  3, "chara": "oboro",     "atr": "b",  "zoen": null},
  {"map": "koori",   "x":   10, "y":  4, "chara": "elise",     "atr": null, "zoen": null},
  {"map": "koori",   "x":   10, "y":  4, "chara": "frederick", "atr": null, "zoen": null},
  {"map": "koori",   "x":   10, "y":  4, "chara": "lissa",     "atr": "b",  "zoen": null},
  {"map": "koori",   "x":   10, "y":  8, "chara": "leo",       "atr": "b",  "zoen": null},
  {"map": "koori",   "x":   11, "y":  5, "chara": "iago",      "atr": "b",  "zoen": null},
  {"map": "koori",   "x":   12, "y":  9, "chara": "camilla",   "atr": null, "zoen": null},
  {"map": "koori",   "x":   12, "y":  9, "chara": "hinoka",    "atr": null, "zoen": null},
  {"map": "koori",   "x":   12, "y":  9, "chara": "ceada",     "atr": "b",  "zoen": null},
  {"map": "koori",   "x":   13, "y":  2, "chara": "lianna",    "atr": "b",  "zoen": null},
  {"map": "koori",   "x":   14, "y":  5, "chara": "sakura",    "atr": null, "zoen": null},
  {"map": "koori",   "x":   14, "y":  5, "chara": "navarre",   "atr": "b",  "zoen": null},
  {"map": "koori",   "x":   16, "y":  2, "chara": "leo",       "atr": null, "zoen": null},
  {"map": "devil",   "x":   2,  "y":  8, "chara": "lyn",       "atr": "s",  "zoen": null},
  {"map": "devil",   "x":   2,  "y":  8, "chara": "camilla",   "atr": "s",  "zoen": null},
  {"map": "devil",   "x":   2,  "y":  8, "chara": "gharnef",   "atr": "s",  "zoen": null},
  {"map": "devil",   "x":   6,  "y":  7, "chara": "takumi",    "atr": null, "zoen": null},
  {"map": "devil",   "x":   6,  "y":  7, "chara": "robin",     "atr": "b",  "zoen": null},
  {"map": "devil",   "x":   7,  "y":  8, "chara": "niles",     "atr": null, "zoen": null},
  {"map": "devil",   "x":   7,  "y":  8, "chara": "chrom",     "atr": null, "zoen": null},
  {"map": "devil",   "x":   7,  "y":  8, "chara": "takumi",    "atr": "b",  "zoen": null},
  {"map": "devil",   "x":   8,  "y":  9, "chara": "tiki",      "atr": "s",  "zoen": null},
  {"map": "devil",   "x":   8,  "y":  9, "chara": "frederick", "atr": "s",  "zoen": null},
  {"map": "devil",   "x":   8,  "y":  9, "chara": "lissa",     "atr": "s",  "zoen": null},
  {"map": "devil",   "x":   8,  "y":  9, "chara": "cordelia",  "atr": "s",  "zoen": null},
  {"map": "devil",   "x":   9,  "y":  5, "chara": "robin",     "atr": null, "zoen": null},
  {"map": "devil",   "x":   9,  "y":  5, "chara": "corrin",    "atr": "b",  "zoen": null},
  {"map": "devil",   "x":   9,  "y":  5, "chara": "cordelia",  "atr": null, "zoen": null},
  {"map": "devil",   "x":   9,  "y":  5, "chara": "xander",    "atr": "b",  "zoen": null},
  {"map": "devil",   "x":   9,  "y":  7, "chara": "lucina",    "atr": null, "zoen": null},
  {"map": "devil",   "x":   9,  "y":  7, "chara": "hinoka",    "atr": null, "zoen": null},
  {"map": "devil",   "x":   9,  "y":  7, "chara": "tiki",      "atr": null, "zoen": null},
  {"map": "devil",   "x":   9,  "y":  7, "chara": "celica",    "atr": null, "zoen": null},
  {"map": "devil",   "x":   9,  "y":  7, "chara": "ceada",     "atr": null, "zoen": null},
  {"map": "devil",   "x":   9,  "y":  7, "chara": "cordelia",  "atr": "b",  "zoen": null},
  {"map": "devil",   "x":   10, "y":  8, "chara": "tiki",      "atr": null, "zoen": null},
  {"map": "devil",   "x":   10, "y":  8, "chara": "minerva",   "atr": "b",  "zoen": null},
  {"map": "devil",   "x":   11, "y":  9, "chara": "tiki",      "atr": null, "zoen": null},
  {"map": "devil",   "x":   11, "y":  9, "chara": "niles",     "atr": "b",  "zoen": null},
  {"map": "devil",   "x":   14, "y":  3, "chara": "oboro",     "atr": null, "zoen": null},
  {"map": "devil",   "x":   14, "y":  3, "chara": "hinoka",    "atr": "b",  "zoen": null},
  {"map": "devil",   "x":   15, "y":  4, "chara": "sakura",    "atr": null, "zoen": null},
  {"map": "devil",   "x":   15, "y":  4, "chara": "anna",      "atr": null, "zoen": null},
  {"map": "devil",   "x":   15, "y":  4, "chara": "elise",     "atr": null, "zoen": null},
  {"map": "devil",   "x":   15, "y":  4, "chara": "lissa",     "atr": "b",  "zoen": null},
  {"map": "devil",   "x":   15, "y":  7, "chara": "iago",      "atr": "b",  "zoen": null},
  {"map": "devil",   "x":   16, "y":  5, "chara": "tiki",      "atr": "b",  "zoen": null},
  {"map": "devil",   "x":   16, "y":  5, "chara": "hinoka",    "atr": null, "zoen": null},
  {"map": "devil",   "x":   16, "y":  5, "chara": "celica",    "atr": "b",  "zoen": null},
  {"map": "devil",   "x":   16, "y":  6, "chara": "frederick", "atr": "b",  "zoen": null},
  {"map": "devil",   "x":   17, "y":  5, "chara": "lyn",       "atr": null, "zoen": null},
  {"map": "devil",   "x":   17, "y":  5, "chara": "owain",     "atr": "b",  "zoen": null},
  {"map": "princess","x":   1,  "y":  5, "chara": "minerva",   "atr": null, "zoen": null},
  {"map": "princess","x":   1,  "y":  5, "chara": "leo",       "atr": null, "zoen": null},
  {"map": "princess","x":   1,  "y":  5, "chara": "frederick", "atr": null, "zoen": null},
  {"map": "princess","x":   1,  "y":  5, "chara": "gharnef",   "atr": null, "zoen": null},
  {"map": "princess","x":   1,  "y":  5, "chara": "tiki",      "atr": "b",  "zoen": null},
  {"map": "princess","x":   2,  "y":  2, "chara": "camilla",   "atr": null, "zoen": null},
  {"map": "princess","x":   2,  "y":  2, "chara": "cordelia",  "atr": null, "zoen": null},
  {"map": "princess","x":   2,  "y":  2, "chara": "hinoka",    "atr": "b",  "zoen": null},
  {"map": "princess","x":   2,  "y":  6, "chara": "gharnef",   "atr": null, "zoen": null},
  {"map": "princess","x":   3,  "y":  5, "chara": "frederick", "atr": null, "zoen": null},
  {"map": "princess","x":   3,  "y":  5, "chara": "robin",     "atr": null, "zoen": null},
  {"map": "princess","x":   3,  "y":  5, "chara": "cordelia",  "atr": "b",  "zoen": null},
  {"map": "princess","x":   3,  "y":  9, "chara": "ryoma",     "atr": null, "zoen": null},
  {"map": "princess","x":   3,  "y":  9, "chara": "camilla",   "atr": null, "zoen": null},
  {"map": "princess","x":   3,  "y":  9, "chara": "frederick", "atr": "b",  "zoen": null},
  {"map": "princess","x":   4,  "y":  8, "chara": "tiki",      "atr": null, "zoen": null},
  {"map": "princess","x":   4,  "y":  8, "chara": "ryoma",     "atr": "b",  "zoen": null},
  {"map": "princess","x":   5,  "y":  9, "chara": "ceada",     "atr": null, "zoen": null},
  {"map": "princess","x":   5,  "y":  9, "chara": "minerva",   "atr": "b",  "zoen": null},
  {"map": "princess","x":   7,  "y":  4, "chara": "elise",     "atr": null, "zoen": null},
  {"map": "princess","x":   7,  "y":  4, "chara": "anna",      "atr": null, "zoen": null},
  {"map": "princess","x":   7,  "y":  4, "chara": "sakura",    "atr": "b",  "zoen": null},
  {"map": "princess","x":   8,  "y":  3, "chara": "owain",     "atr": "b",  "zoen": null},
  {"map": "princess","x":   9,  "y":  1, "chara": "minerva",   "atr": null, "zoen": null},
  {"map": "princess","x":   9,  "y":  1, "chara": "linde",     "atr": "b",  "zoen": null},
  {"map": "princess","x":   9,  "y":  1, "chara": "anna",      "atr": null, "zoen": null},
  {"map": "princess","x":   9,  "y":  1, "chara": "niles",     "atr": "b",  "zoen": null},
  {"map": "princess","x":   11, "y":  8, "chara": "validar",   "atr": "s",  "zoen": null},
  {"map": "princess","x":   11, "y":  8, "chara": "iago",      "atr": "s",  "zoen": null},
  {"map": "princess","x":   12, "y":  9, "chara": "oboro",     "atr": "b",  "zoen": null},
  {"map": "princess","x":   15, "y":  9, "chara": "hinoka",    "atr": null, "zoen": null},
  {"map": "princess","x":   15, "y":  9, "chara": "sakura",    "atr": null, "zoen": null},
  {"map": "princess","x":   15, "y":  9, "chara": "lianna",    "atr": "b",  "zoen": null},
  {"map": "princess","x":   17, "y":  3, "chara": "linde",     "atr": "b",  "zoen": null},
  {"map": "norda",   "x":   2,  "y":  6, "chara": "sakura",    "atr": null, "zoen": null},
  {"map": "norda",   "x":   2,  "y":  6, "chara": "robin",     "atr": "b",  "zoen": null},
  {"map": "norda",   "x":   3,  "y":  5, "chara": "iago",      "atr": null, "zoen": null},
  {"map": "norda",   "x":   3,  "y":  5, "chara": "lissa",     "atr": null, "zoen": null},
  {"map": "norda",   "x":   3,  "y":  5, "chara": "minerva",   "atr": null, "zoen": null},
  {"map": "norda",   "x":   3,  "y":  5, "chara": "validar",   "atr": "b",  "zoen": null},
  {"map": "norda",   "x":   3,  "y":  7, "chara": "tiki",      "atr": null, "zoen": null},
  {"map": "norda",   "x":   3,  "y":  7, "chara": "gharnef",   "atr": null, "zoen": null},
  {"map": "norda",   "x":   3,  "y":  7, "chara": "elise",     "atr": "b",  "zoen": null},
  {"map": "norda",   "x":   4,  "y":  3, "chara": "gharnef",   "atr": "s",  "zoen": null},
  {"map": "norda",   "x":   4,  "y":  3, "chara": "tiki",      "atr": "s",  "zoen": null},
  {"map": "norda",   "x":   4,  "y":  3, "chara": "minerva",   "atr": "s",  "zoen": null},
  {"map": "norda",   "x":   4,  "y":  3, "chara": "frederick", "atr": "s",  "zoen": null},
  {"map": "norda",   "x":   5,  "y":  2, "chara": "celica",    "atr": null, "zoen": null},
  {"map": "norda",   "x":   5,  "y":  2, "chara": "iago",      "atr": null, "zoen": null},
  {"map": "norda",   "x":   5,  "y":  2, "chara": "xander",    "atr": null, "zoen": null},
  {"map": "norda",   "x":   5,  "y":  2, "chara": "leo",       "atr": null, "zoen": null},
  {"map": "norda",   "x":   5,  "y":  2, "chara": "darios",    "atr": "b",  "zoen": null},
  {"map": "norda",   "x":   6,  "y":  4, "chara": "chrom",     "atr": "b",  "zoen": null},
  {"map": "norda",   "x":   7,  "y":  3, "chara": "oboro",     "atr": null, "zoen": null},
  {"map": "norda",   "x":   7,  "y":  3, "chara": "tiki",      "atr": null, "zoen": null},
  {"map": "norda",   "x":   7,  "y":  3, "chara": "hinoka",    "atr": null, "zoen": null},
  {"map": "norda",   "x":   7,  "y":  3, "chara": "lissa",     "atr": "b",  "zoen": null},
  {"map": "norda",   "x":   8,  "y":  2, "chara": "tiki",      "atr": null, "zoen": null},
  {"map": "norda",   "x":   8,  "y":  2, "chara": "cordelia",  "atr": "b",  "zoen": null},
  {"map": "norda",   "x":   8,  "y":  2, "chara": "sakura",    "atr": null, "zoen": null},
  {"map": "norda",   "x":   8,  "y":  2, "chara": "hinoka",    "atr": "b",  "zoen": null},
  {"map": "norda",   "x":   12, "y":  2, "chara": "tiki",      "atr": null, "zoen": null},
  {"map": "norda",   "x":   12, "y":  2, "chara": "ceada",     "atr": "b",  "zoen": null},
  {"map": "norda",   "x":   13, "y":  7, "chara": "niles",     "atr": "b",  "zoen": null},
  {"map": "norda",   "x":   14, "y":  4, "chara": "ryoma",     "atr": "s",  "zoen": null},
  {"map": "norda",   "x":   14, "y":  4, "chara": "niles",     "atr": "s",  "zoen": null},
  {"map": "norda",   "x":   14, "y":  6, "chara": "leo",       "atr": "b",  "zoen": null},
  {"map": "norda",   "x":   15, "y":  3, "chara": "elise",     "atr": null, "zoen": null},
  {"map": "norda",   "x":   15, "y":  3, "chara": "sakura",    "atr": "b",  "zoen": null},
  {"map": "norda",   "x":   15, "y":  7, "chara": "rowan",     "atr": "b",  "zoen": null},
  {"map": "norda",   "x":   16, "y":  2, "chara": "navarre",   "atr": null, "zoen": null},
  {"map": "norda",   "x":   16, "y":  2, "chara": "takumi",    "atr": null, "zoen": null},
  {"map": "norda",   "x":   16, "y":  2, "chara": "marth",     "atr": "b",  "zoen": null},
  {"map": "koori",   "x":   2,  "y":  8, "chara": "gharnef",   "atr": "b",  "zoen": null},
  {"map": "koori",   "x":   2,  "y":  8, "chara": "corrin",    "atr": null, "zoen": null},
  {"map": "koori",   "x":   2,  "y":  8, "chara": "validar",   "atr": null, "zoen": null},
  {"map": "koori",   "x":   2,  "y":  8, "chara": "iago",      "atr": null, "zoen": null},
  {"map": "koori",   "x":   5,  "y":  5, "chara": "owain",     "atr": null, "zoen": null},
  {"map": "koori",   "x":   5,  "y":  5, "chara": "niles",     "atr": "b",  "zoen": null},
  {"map": "koori",   "x":   5,  "y":  5, "chara": "takumi",    "atr": null, "zoen": null},
  {"map": "koori",   "x":   5,  "y":  5, "chara": "robin",     "atr": "b",  "zoen": null},
  {"map": "koori",   "x":   6,  "y":  2, "chara": "validar",   "atr": "b",  "zoen": null},
  {"map": "devil",   "x":   12, "y":  4, "chara": "oboro",     "atr": null, "zoen": null},
  {"map": "devil",   "x":   12, "y":  4, "chara": "sakura",    "atr": "b",  "zoen": null},
  {"map": "devil",   "x":   13, "y":  8, "chara": "rowan",     "atr": null, "zoen": null},
  {"map": "devil",   "x":   13, "y":  8, "chara": "tiki",      "atr": null, "zoen": null},
  {"map": "devil",   "x":   13, "y":  8, "chara": "lissa",     "atr": "b",  "zoen": null},
  {"map": "princess","x":   2,  "y":  8, "chara": "elise",     "atr": "s",  "zoen": null},
  {"map": "princess","x":   2,  "y":  8, "chara": "cordelia",  "atr": "s",  "zoen": null},
  {"map": "princess","x":   2,  "y":  8, "chara": "navarre",   "atr": "s",  "zoen": null},
  {"map": "princess","x":   2,  "y":  8, "chara": "rowan",     "atr": "s",  "zoen": null},
  {"map": "princess","x":   2,  "y":  8, "chara": "robin",     "atr": "s",  "zoen": null},
  {"map": "princess","x":   2,  "y":  8, "chara": "hinoka",    "atr": "s",  "zoen": null},
  {"map": "princess","x":   6,  "y":  2, "chara": "corrin",    "atr": null, "zoen": null},
  {"map": "princess","x":   12, "y":  2, "chara": "corrin",    "atr": null, "zoen": null},
  {"map": "princess","x":   12, "y":  2, "chara": "takumi",    "atr": null, "zoen": null},
  {"map": "princess","x":   12, "y":  2, "chara": "robin",     "atr": "b",  "zoen": null},
  {"map": "princess","x":   16, "y":  2, "chara": "leo",       "atr": null, "zoen": null},
  {"map": "princess","x":   16, "y":  2, "chara": "takumi",    "atr": null, "zoen": null},
  {"map": "princess","x":   16, "y":  2, "chara": "tiki",      "atr": null, "zoen": null},
  {"map": "princess","x":   16, "y":  2, "chara": "sakura",    "atr": "b",  "zoen": null},
  {"map": "norda",   "x":   2,  "y":  8, "chara": "navarre",   "atr": null, "zoen": null},
  {"map": "norda",   "x":   2,  "y":  8, "chara": "lyn",       "atr": null, "zoen": null},
  {"map": "norda",   "x":   2,  "y":  8, "chara": "takumi",    "atr": "b",  "zoen": null},
  {"map": "norda",   "x":   6,  "y":  6, "chara": "tiki",      "atr": null, "zoen": null},
  {"map": "norda",   "x":   6,  "y":  6, "chara": "ceada",     "atr": "b",  "zoen": null},
  {"map": "norda",   "x":   6,  "y":  6, "chara": "camilla",   "atr": null, "zoen": null},
  {"map": "norda",   "x":   6,  "y":  6, "chara": "minerva",   "atr": "b",  "zoen": null},
  {"map": "norda",   "x":   8,  "y":  8, "chara": "corrin",    "atr": "b",  "zoen": null},
  {"map": "densetu", "x":   4,  "y":  2, "chara": "lissa",     "atr": null, "zoen": null},
  {"map": "densetu", "x":   4,  "y":  2, "chara": "frederick", "atr": null, "zoen": null},
  {"map": "densetu", "x":   4,  "y":  2, "chara": "lianna",    "atr": null, "zoen": null},
  {"map": "densetu", "x":   4,  "y":  2, "chara": "camilla",   "atr": "b",  "zoen": null},
  {"map": "densetu", "x":   5,  "y":  1, "chara": "robin",     "atr": null, "zoen": null},
  {"map": "densetu", "x":   5,  "y":  1, "chara": "tharja",    "atr": "b",  "zoen": null},
  {"map": "densetu", "x":   5,  "y":  1, "chara": "tiki",      "atr": null, "zoen": null},
  {"map": "densetu", "x":   5,  "y":  1, "chara": "hinoka",    "atr": "b",  "zoen": null},
  {"map": "densetu", "x":   7,  "y":  7, "chara": "sakura",    "atr": null, "zoen": null},
  {"map": "densetu", "x":   7,  "y":  7, "chara": "takumi",    "atr": "b",  "zoen": null},
  {"map": "densetu", "x":   7,  "y":  7, "chara": "frederick", "atr": null, "zoen": null},
  {"map": "densetu", "x":   7,  "y":  7, "chara": "camilla",   "atr": "b",  "zoen": null},
  {"map": "densetu", "x":   8,  "y":  5, "chara": "chrom",     "atr": "s",  "zoen": null},
  {"map": "densetu", "x":   8,  "y":  5, "chara": "tharja",    "atr": "s",  "zoen": null},
  {"map": "densetu", "x":   8,  "y":  5, "chara": "olivia",    "atr": "s",  "zoen": null},
  {"map": "densetu", "x":   8,  "y":  5, "chara": "lissa",     "atr": "s",  "zoen": null},
  {"map": "densetu", "x":   9,  "y":  7, "chara": "darios",    "atr": "b",  "zoen": null},
  {"map": "densetu", "x":   11, "y":  2, "chara": "oboro",     "atr": "b",  "zoen": null},
  {"map": "densetu", "x":   11, "y":  4, "chara": "robin",     "atr": null, "zoen": null},
  {"map": "densetu", "x":   11, "y":  4, "chara": "takumi",    "atr": null, "zoen": null},
  {"map": "densetu", "x":   11, "y":  4, "chara": "corrin",    "atr": null, "zoen": null},
  {"map": "densetu", "x":   11, "y":  4, "chara": "leo",       "atr": "b",  "zoen": null},
  {"map": "densetu", "x":   13, "y":  4, "chara": "oboro",     "atr": null, "zoen": null},
  {"map": "densetu", "x":   13, "y":  4, "chara": "lissa",     "atr": "b",  "zoen": null},
  {"map": "densetu", "x":   13, "y":  6, "chara": "niles",     "atr": null, "zoen": null},
  {"map": "densetu", "x":   13, "y":  6, "chara": "tiki",      "atr": null, "zoen": null},
  {"map": "densetu", "x":   13, "y":  6, "chara": "anna",      "atr": "b",  "zoen": null},
  {"map": "densetu", "x":   14, "y":  2, "chara": "niles",     "atr": null, "zoen": null},
  {"map": "densetu", "x":   14, "y":  2, "chara": "ceada",     "atr": null, "zoen": null},
  {"map": "densetu", "x":   14, "y":  2, "chara": "cordelia",  "atr": "b",  "zoen": null},
  {"map": "densetu", "x":   14, "y":  3, "chara": "olivia",    "atr": null, "zoen": null},
  {"map": "densetu", "x":   14, "y":  3, "chara": "ceada",     "atr": null, "zoen": null},
  {"map": "densetu", "x":   14, "y":  3, "chara": "navarre",   "atr": "b",  "zoen": null},
  {"map": "densetu", "x":   4,  "y":  4, "chara": "chrom",     "atr": null, "zoen": null},
  {"map": "densetu", "x":   4,  "y":  4, "chara": "lissa",     "atr": "b",  "zoen": null},
  {"map": "densetu", "x":   4,  "y":  9, "chara": "gharnef",   "atr": "b",  "zoen": null},
  {"map": "densetu", "x":   6,  "y":  6, "chara": "niles",     "atr": "b",  "zoen": null},
  {"map": "densetu", "x":   7,  "y":  5, "chara": "camilla",   "atr": null, "zoen": null},
  {"map": "densetu", "x":   7,  "y":  5, "chara": "oboro",     "atr": null, "zoen": null},
  {"map": "densetu", "x":   7,  "y":  5, "chara": "cordelia",  "atr": "b",  "zoen": null},
  {"map": "densetu", "x":   7,  "y":  9, "chara": "tiki",      "atr": null, "zoen": null},
  {"map": "densetu", "x":   7,  "y":  9, "chara": "anna",      "atr": "b",  "zoen": null},
  {"map": "densetu", "x":   7,  "y":  9, "chara": "sakura",    "atr": null, "zoen": null},
  {"map": "densetu", "x":   7,  "y":  9, "chara": "takumi",    "atr": "b",  "zoen": null},
  {"map": "densetu", "x":   8,  "y":  6, "chara": "frederick", "atr": null, "zoen": null},
  {"map": "densetu", "x":   8,  "y":  6, "chara": "niles",     "atr": "b",  "zoen": null},
  {"map": "densetu", "x":   10, "y":  8, "chara": "leo",       "atr": "s",  "zoen": null},
  {"map": "densetu", "x":   10, "y":  8, "chara": "celica",    "atr": "s",  "zoen": null},
  {"map": "densetu", "x":   10, "y":  8, "chara": "tiki",      "atr": "s",  "zoen": null},
  {"map": "densetu", "x":   13, "y":  5, "chara": "frederick", "atr": "b",  "zoen": null},
  {"map": "densetu", "x":   13, "y":  7, "chara": "validar",   "atr": null, "zoen": null},
  {"map": "densetu", "x":   13, "y":  7, "chara": "sakura",    "atr": null, "zoen": null},
  {"map": "densetu", "x":   13, "y":  7, "chara": "tiki",      "atr": null, "zoen": null},
  {"map": "densetu", "x":   13, "y":  7, "chara": "iago",      "atr": "b",  "zoen": null},
  {"map": "densetu", "x":   13, "y":  9, "chara": "tiki",      "atr": null, "zoen": null},
  {"map": "densetu", "x":   13, "y":  9, "chara": "lianna",    "atr": null, "zoen": null},
  {"map": "caravan", "x":   2,  "y":  2, "chara": "gharnef",   "atr": null, "zoen": null},
  {"map": "caravan", "x":   2,  "y":  2, "chara": "camilla",   "atr": null, "zoen": null},
  {"map": "caravan", "x":   2,  "y":  2, "chara": "validar",   "atr": "b",  "zoen": null},
  {"map": "caravan", "x":   2,  "y":  5, "chara": "anna",      "atr": "s",  "zoen": null},
  {"map": "caravan", "x":   2,  "y":  5, "chara": "lianna",    "atr": "s",  "zoen": null},
  {"map": "caravan", "x":   2,  "y":  5, "chara": "lucina",    "atr": "s",  "zoen": null},
  {"map": "caravan", "x":   2,  "y":  5, "chara": "tiki",      "atr": "s",  "zoen": null},
  {"map": "caravan", "x":   3,  "y":  4, "chara": "hinoka",    "atr": null, "zoen": null},
  {"map": "caravan", "x":   3,  "y":  4, "chara": "tiki",      "atr": null, "zoen": null},
  {"map": "caravan", "x":   3,  "y":  4, "chara": "elise",     "atr": null, "zoen": null},
  {"map": "caravan", "x":   3,  "y":  4, "chara": "tharja",    "atr": "b",  "zoen": null},
  {"map": "caravan", "x":   5,  "y":  4, "chara": "tharja",    "atr": null, "zoen": null},
  {"map": "caravan", "x":   5,  "y":  4, "chara": "robin",     "atr": null, "zoen": null},
  {"map": "caravan", "x":   5,  "y":  4, "chara": "chrom",     "atr": "b",  "zoen": null},
  {"map": "caravan", "x":   6,  "y":  2, "chara": "iago",      "atr": null, "zoen": null},
  {"map": "caravan", "x":   6,  "y":  2, "chara": "gharnef",   "atr": "b",  "zoen": null},
  {"map": "caravan", "x":   6,  "y":  8, "chara": "lucina",    "atr": "b",  "zoen": null},
  {"map": "caravan", "x":   7,  "y":  3, "chara": "lissa",     "atr": null, "zoen": null},
  {"map": "caravan", "x":   7,  "y":  3, "chara": "frederick", "atr": null, "zoen": null},
  {"map": "caravan", "x":   7,  "y":  3, "chara": "hinoka",    "atr": null, "zoen": null},
  {"map": "caravan", "x":   7,  "y":  3, "chara": "ceada",     "atr": null, "zoen": null},
  {"map": "caravan", "x":   7,  "y":  3, "chara": "anna",      "atr": null, "zoen": null},
  {"map": "caravan", "x":   7,  "y":  3, "chara": "cordelia",  "atr": "b",  "zoen": null},
  {"map": "caravan", "x":   7,  "y":  5, "chara": "tharja",    "atr": null, "zoen": null},
  {"map": "caravan", "x":   7,  "y":  5, "chara": "frederick", "atr": null, "zoen": null},
  {"map": "caravan", "x":   7,  "y":  5, "chara": "celica",    "atr": "b",  "zoen": null},
  {"map": "caravan", "x":   7,  "y":  7, "chara": "tiki",      "atr": null, "zoen": null},
  {"map": "caravan", "x":   8,  "y":  8, "chara": "robin",     "atr": "b",  "zoen": null},
  {"map": "caravan", "x":   10, "y":  4, "chara": "niles",     "atr": "b",  "zoen": null},
  {"map": "caravan", "x":   10, "y":  6, "chara": "xander",    "atr": null, "zoen": null},
  {"map": "caravan", "x":   10, "y":  6, "chara": "elise",     "atr": null, "zoen": null},
  {"map": "caravan", "x":   10, "y":  6, "chara": "frederick", "atr": "b",  "zoen": null},
  {"map": "caravan", "x":   14, "y":  9, "chara": "tiki",      "atr": null, "zoen": null},
  {"map": "caravan", "x":   14, "y":  9, "chara": "sakura",    "atr": null, "zoen": null},
  {"map": "caravan", "x":   14, "y":  9, "chara": "camilla",   "atr": null, "zoen": null},
  {"map": "caravan", "x":   14, "y":  9, "chara": "lissa",     "atr": "b",  "zoen": null},
  {"map": "caravan", "x":   15, "y":  3, "chara": "tiki",      "atr": null, "zoen": null},
  {"map": "caravan", "x":   15, "y":  3, "chara": "oboro",     "atr": "b",  "zoen": null},
  {"map": "caravan", "x":   15, "y":  3, "chara": "ryoma",     "atr": null, "zoen": null},
  {"map": "caravan", "x":   15, "y":  3, "chara": "owain",     "atr": "b",  "zoen": null},
  {"map": "kamigami","x":   2,  "y":  6, "chara": "validar",   "atr": "b",  "zoen": null},
  {"map": "kamigami","x":   9,  "y":  5, "chara": "camilla",   "atr": null, "zoen": null},
  {"map": "kamigami","x":   9,  "y":  5, "chara": "niles",     "atr": "b",  "zoen": null},
  {"map": "kamigami","x":   11, "y":  2, "chara": "leo",       "atr": null, "zoen": null},
  {"map": "kamigami","x":   11, "y":  2, "chara": "lissa",     "atr": "b",  "zoen": null},
  {"map": "akuno",   "x":   14, "y":  2, "chara": "cordelia",  "atr": null, "zoen": null},
  {"map": "akuno",   "x":   14, "y":  2, "chara": "owain",     "atr": "b",  "zoen": null},
  {"map": "akuno",   "x":   14, "y":  2, "chara": "corrin",    "atr": null, "zoen": null},
  {"map": "akuno",   "x":   14, "y":  2, "chara": "oboro",     "atr": "b",  "zoen": null},
  {"map": "densetu", "x":   13, "y":  8, "chara": "rowan",     "atr": "b",  "zoen": null},
  {"map": "devil",   "x":   3,  "y":  4, "chara": "validar",   "atr": "b",  "zoen": null},
  {"map": "devil",   "x":   3,  "y":  7, "chara": "lissa",     "atr": null, "zoen": null},
  {"map": "devil",   "x":   3,  "y":  7, "chara": "tiki",      "atr": "b",  "zoen": null},
  {"map": "devil",   "x":   5,  "y":  2, "chara": "camilla",   "atr": "b",  "zoen": null},
  {"map": "kamigami","x":   9,  "y":  1, "chara": "gharnef",   "atr": null, "zoen": null},
  {"map": "kamigami","x":   9,  "y":  1, "chara": "validar",   "atr": "b",  "zoen": null},
  {"map": "nageki",  "x":   2,  "y":  8, "chara": "chrom",     "atr": "b",  "zoen": null},
  {"map": "nageki",  "x":   7,  "y":  1, "chara": "ceada",     "atr": null, "zoen": null},
  {"map": "nageki",  "x":   7,  "y":  1, "chara": "marth",     "atr": "b",  "zoen": null},
  {"map": "nageki",  "x":   7,  "y":  1, "chara": "robin",     "atr": null, "zoen": null},
  {"map": "nageki",  "x":   7,  "y":  1, "chara": "chrom",     "atr": "b",  "zoen": null},
  {"map": "princess","x":   2,  "y":  1, "chara": "xander",    "atr": "b",  "zoen": null},
  {"map": "seiou",   "x":   4,  "y":  4, "chara": "chrom",     "atr": null, "zoen": null},
  {"map": "seiou",   "x":   4,  "y":  4, "chara": "lissa",     "atr": "b",  "zoen": null},
  {"map": "seiou",   "x":   4,  "y":  9, "chara": "gharnef",   "atr": "b",  "zoen": null},
  {"map": "seiou",   "x":   6,  "y":  6, "chara": "niles",     "atr": "b",  "zoen": null},
  {"map": "seiou",   "x":   7,  "y":  5, "chara": "camilla",   "atr": null, "zoen": null},
  {"map": "seiou",   "x":   7,  "y":  5, "chara": "oboro",     "atr": null, "zoen": null},
  {"map": "seiou",   "x":   7,  "y":  5, "chara": "olivia",    "atr": null, "zoen": null},
  {"map": "seiou",   "x":   7,  "y":  5, "chara": "cordelia",  "atr": "b",  "zoen": null},
  {"map": "seiou",   "x":   7,  "y":  9, "chara": "tiki",      "atr": null, "zoen": null},
  {"map": "seiou",   "x":   7,  "y":  9, "chara": "anna",      "atr": "b",  "zoen": null},
  {"map": "seiou",   "x":   7,  "y":  9, "chara": "sakura",    "atr": null, "zoen": null},
  {"map": "seiou",   "x":   7,  "y":  9, "chara": "takumi",    "atr": "b",  "zoen": null},
  {"map": "seiou",   "x":   8,  "y":  6, "chara": "frederick", "atr": null, "zoen": null},
  {"map": "seiou",   "x":   8,  "y":  6, "chara": "niles",     "atr": "b",  "zoen": null},
  {"map": "seiou",   "x":   10, "y":  8, "chara": "leo",       "atr": "s",  "zoen": null},
  {"map": "seiou",   "x":   10, "y":  8, "chara": "celica",    "atr": "s",  "zoen": null},
  {"map": "seiou",   "x":   10, "y":  8, "chara": "tiki",      "atr": "s",  "zoen": null},
  {"map": "seiou",   "x":   13, "y":  5, "chara": "frederick", "atr": "b",  "zoen": null},
  {"map": "seiou",   "x":   13, "y":  7, "chara": "validar",   "atr": null, "zoen": null},
  {"map": "seiou",   "x":   13, "y":  7, "chara": "sakura",    "atr": null, "zoen": null},
  {"map": "seiou",   "x":   13, "y":  7, "chara": "tiki",      "atr": null, "zoen": null},
  {"map": "seiou",   "x":   13, "y":  7, "chara": "iago",      "atr": "b",  "zoen": null},
  {"map": "seiou",   "x":   13, "y":  9, "chara": "tiki",      "atr": null, "zoen": null},
  {"map": "seiou",   "x":   13, "y":  9, "chara": "lianna",    "atr": null, "zoen": null},
  {"map": "seiou",   "x":   13, "y":  9, "chara": "tharja",    "atr": "b",  "zoen": null},
  {"map": "eiyuu",   "x":   5,  "y":  7, "chara": "camilla",   "atr": null, "zoen": null},
  {"map": "eiyuu",   "x":   5,  "y":  7, "chara": "elise",     "atr": null, "zoen": null},
  {"map": "eiyuu",   "x":   5,  "y":  7, "chara": "xander",    "atr": "b",  "zoen": null},
  {"map": "eiyuu",   "x":   9,  "y":  3, "chara": "corrin",    "atr": null, "zoen": null},
  {"map": "eiyuu",   "x":   9,  "y":  3, "chara": "iago",      "atr": "b",  "zoen": null},
  {"map": "eiyuu",   "x":   9,  "y":  5, "chara": "darios",    "atr": "b",  "zoen": null},
  {"map": "eiyuu",   "x":   9,  "y":  8, "chara": "robin",     "atr": null, "zoen": null},
  {"map": "eiyuu",   "x":   9,  "y":  8, "chara": "validar",   "atr": "b",  "zoen": null},
  {"map": "eiyuu",   "x":   12, "y":  2, "chara": "gharnef",   "atr": "b",  "zoen": null},
  {"map": "eiyuu",   "x":   12, "y":  8, "chara": "oboro",     "atr": null, "zoen": null},
  {"map": "eiyuu",   "x":   12, "y":  8, "chara": "takumi",    "atr": "b",  "zoen": null},
  {"map": "eiyuu",   "x":   13, "y":  7, "chara": "hinoka",    "atr": null, "zoen": null},
  {"map": "eiyuu",   "x":   13, "y":  7, "chara": "sakura",    "atr": null, "zoen": null},
  {"map": "eiyuu",   "x":   13, "y":  7, "chara": "ryoma",     "atr": "b",  "zoen": null},
  {"map": "unmei",   "x":   5,  "y":  6, "chara": "robin",     "atr": "3",  "zoen": null},
  {"map": "unmei",   "x":   5,  "y":  6, "chara": "lucina",    "atr": "4",  "zoen": null},
  {"map": "unmei",   "x":   5,  "y":  6, "chara": "chrom",     "atr": "4",  "zoen": 1},
  {"map": "unmei",   "x":   5,  "y":  6, "chara": "lianna",    "atr": "5",  "zoen": null},
  {"map": "unmei",   "x":   5,  "y":  6, "chara": "rowan",     "atr": "5",  "zoen": 1},
  {"map": "unmei",   "x":   5,  "y":  6, "chara": "owain",     "atr": "6",  "zoen": null},
  {"map": "unmei",   "x":   17, "y":  2, "chara": "ryoma",     "atr": "3",  "zoen": null},
  {"map": "unmei",   "x":   17, "y":  2, "chara": "takumi",    "atr": "4",  "zoen": null},
  {"map": "unmei",   "x":   17, "y":  2, "chara": "camilla",   "atr": "4",  "zoen": 1},
  {"map": "unmei",   "x":   17, "y":  2, "chara": "chrom",     "atr": "5",  "zoen": null},
  {"map": "unmei",   "x":   17, "y":  2, "chara": "robin",     "atr": "5",  "zoen": 1},
  {"map": "unmei",   "x":   17, "y":  2, "chara": "sakura",    "atr": "6",  "zoen": null},
  {"map": "unmei",   "x":   17, "y":  2, "chara": "xander",    "atr": "6",  "zoen": 1},
  {"map": "unmei",   "x":   17, "y":  2, "chara": "lianna",    "atr": "6",  "zoen": 1},
  {"map": "sonote",  "x":   1,  "y":  4, "chara": "elise",     "atr": "3",  "zoen": null},
  {"map": "sonote",  "x":   1,  "y":  4, "chara": "niles",     "atr": "4",  "zoen": null},
  {"map": "sonote",  "x":   1,  "y":  4, "chara": "cordelia",  "atr": "4",  "zoen": 1},
  {"map": "sonote",  "x":   1,  "y":  4, "chara": "lianna",    "atr": "5",  "zoen": null},
  {"map": "sonote",  "x":   1,  "y":  4, "chara": "owain",     "atr": "5",  "zoen": 1},
  {"map": "sonote",  "x":   1,  "y":  4, "chara": "corrin",    "atr": "6",  "zoen": null},
  {"map": "sonote",  "x":   1,  "y":  4, "chara": "xander",    "atr": "6",  "zoen": 1},
  {"map": "sonote",  "x":   16, "y":  4, "chara": "cordelia",  "atr": "3",  "zoen": null},
  {"map": "sonote",  "x":   16, "y":  4, "chara": "ryoma",     "atr": "4",  "zoen": null},
  {"map": "sonote",  "x":   16, "y":  4, "chara": "xander",    "atr": "4",  "zoen": 1},
  {"map": "sonote",  "x":   16, "y":  4, "chara": "oboro",     "atr": "5",  "zoen": null},
  {"map": "sonote",  "x":   16, "y":  4, "chara": "elise",     "atr": "5",  "zoen": 1},
  {"map": "sonote",  "x":   16, "y":  4, "chara": "chrom",     "atr": "6",  "zoen": null},
  {"map": "sonote",  "x":   16, "y":  4, "chara": "lucina",    "atr": "6",  "zoen": 1},
  {"map": "sonote",  "x":   16, "y":  4, "chara": "corrin",    "atr": "6",  "zoen": 1},
  {"map": "akuno",   "x":   12, "y":  4, "chara": "gharnef",   "atr": "3",  "zoen": null},
  {"map": "akuno",   "x":   12, "y":  4, "chara": "lissa",     "atr": "4",  "zoen": null},
  {"map": "akuno",   "x":   12, "y":  4, "chara": "navarre",   "atr": "4",  "zoen": 1},
  {"map": "akuno",   "x":   12, "y":  4, "chara": "ceada",     "atr": "5",  "zoen": null},
  {"map": "akuno",   "x":   12, "y":  4, "chara": "marth",     "atr": "5",  "zoen": 1},
  {"map": "akuno",   "x":   12, "y":  4, "chara": "oboro",     "atr": "6",  "zoen": null},
  {"map": "akuno",   "x":   12, "y":  4, "chara": "frederick", "atr": "6",  "zoen": 1},
  {"map": "kiaran",  "x":   17, "y":  7, "chara": "lucina",    "atr": "6",  "zoen": 1},
  {"map": "kiaran",  "x":   14, "y":  7, "chara": "marth",     "atr": "3",  "zoen": null},
  {"map": "kiaran",  "x":   14, "y":  7, "chara": "corrin",    "atr": "4",  "zoen": null},
  {"map": "kiaran",  "x":   14, "y":  7, "chara": "robin",     "atr": "4",  "zoen": 1},
  {"map": "kiaran",  "x":   14, "y":  7, "chara": "xander",    "atr": "5",  "zoen": null},
  {"map": "kiaran",  "x":   14, "y":  7, "chara": "leo",       "atr": "5",  "zoen": 1},
  {"map": "kiaran",  "x":   14, "y":  7, "chara": "validar",   "atr": "6",  "zoen": null},
  {"map": "kiaran",  "x":   14, "y":  7, "chara": "niles",     "atr": "6",  "zoen": 1},
  {"map": "kiaran",  "x":   14, "y":  7, "chara": "navarre",   "atr": "6",  "zoen": 1},
  {"map": "kiaran",  "x":   17, "y":  7, "chara": "iago",      "atr": "3",  "zoen": null},
  {"map": "kiaran",  "x":   17, "y":  7, "chara": "owain",     "atr": "4",  "zoen": null},
  {"map": "kiaran",  "x":   17, "y":  7, "chara": "frederick", "atr": "4",  "zoen": 1},
  {"map": "kiaran",  "x":   17, "y":  7, "chara": "camilla",   "atr": "5",  "zoen": null},
  {"map": "kiaran",  "x":   17, "y":  7, "chara": "xander",    "atr": "5",  "zoen": 1},
  {"map": "kiaran",  "x":   17, "y":  7, "chara": "marth",     "atr": "6",  "zoen": null},
  {"map": "saikai",  "x":   8,  "y":  5, "chara": "leo",       "atr": "4",  "zoen": null},
  {"map": "saikai",  "x":   8,  "y":  5, "chara": "frederick", "atr": "5",  "zoen": null},
  {"map": "saikai",  "x":   8,  "y":  5, "chara": "cordelia",  "atr": "5",  "zoen": 1},
  {"map": "saikai",  "x":   8,  "y":  5, "chara": "elise",     "atr": "6",  "zoen": null},
  {"map": "saikai",  "x":   8,  "y":  5, "chara": "robin",     "atr": "6",  "zoen": 1},
  {"map": "saikai",  "x":   17, "y":  4, "chara": "darios",    "atr": "3",  "zoen": null},
  {"map": "saikai",  "x":   17, "y":  4, "chara": "tiki",      "atr": "4",  "zoen": null},
  {"map": "saikai",  "x":   17, "y":  4, "chara": "marth",     "atr": "4",  "zoen": 1},
  {"map": "saikai",  "x":   17, "y":  4, "chara": "leo",       "atr": "5",  "zoen": null},
  {"map": "saikai",  "x":   17, "y":  4, "chara": "celica",    "atr": "5",  "zoen": 1},
  {"map": "saikai",  "x":   17, "y":  4, "chara": "gharnef",   "atr": "6",  "zoen": null},
  {"map": "saikai",  "x":   17, "y":  4, "chara": "iago",      "atr": "6",  "zoen": 1},
  {"map": "saikai",  "x":   17, "y":  4, "chara": "velezark",  "atr": "6",  "zoen": 1},
  {"map": "saikai",  "x":   17, "y":  4, "chara": "gharnef",   "atr": "6",  "zoen": 1},
  {"map": "eiyuu",   "x":   9,  "y":  6, "chara": "robin",     "atr": "3",  "zoen": null},
  {"map": "eiyuu",   "x":   9,  "y":  6, "chara": "chrom",     "atr": "4",  "zoen": null},
  {"map": "eiyuu",   "x":   9,  "y":  6, "chara": "cordelia",  "atr": "4",  "zoen": 1},
  {"map": "eiyuu",   "x":   9,  "y":  6, "chara": "owain",     "atr": "5",  "zoen": null},
  {"map": "eiyuu",   "x":   9,  "y":  6, "chara": "lucina",    "atr": "5",  "zoen": 1},
  {"map": "eiyuu",   "x":   9,  "y":  6, "chara": "lissa",     "atr": "6",  "zoen": null},
  {"map": "eiyuu",   "x":   9,  "y":  6, "chara": "frederick", "atr": "6",  "zoen": 1},
  {"map": "nageki",  "x":   6,  "y":  4, "chara": "validar",   "atr": "3",  "zoen": null},
  {"map": "nageki",  "x":   6,  "y":  4, "chara": "xander",    "atr": "4",  "zoen": null},
  {"map": "nageki",  "x":   6,  "y":  4, "chara": "celica",    "atr": "4",  "zoen": 1},
  {"map": "nageki",  "x":   6,  "y":  4, "chara": "ryoma",     "atr": "5",  "zoen": null},
  {"map": "nageki",  "x":   6,  "y":  4, "chara": "navarre",   "atr": "5",  "zoen": 1},
  {"map": "nageki",  "x":   6,  "y":  4, "chara": "tiki",      "atr": "6",  "zoen": null},
  {"map": "nageki",  "x":   6,  "y":  4, "chara": "lyn",       "atr": "6",  "zoen": 1},
  {"map": "nageki",  "x":   12, "y":  6, "chara": "elise",     "atr": "3",  "zoen": null},
  {"map": "nageki",  "x":   12, "y":  6, "chara": "niles",     "atr": "4",  "zoen": null},
  {"map": "nageki",  "x":   12, "y":  6, "chara": "owain",     "atr": "4",  "zoen": 1},
  {"map": "nageki",  "x":   12, "y":  6, "chara": "lianna",    "atr": "5",  "zoen": null},
  {"map": "nageki",  "x":   12, "y":  6, "chara": "oboro",     "atr": "5",  "zoen": 1},
  {"map": "nageki",  "x":   12, "y":  6, "chara": "xander",    "atr": "6",  "zoen": null},
  {"map": "nageki",  "x":   12, "y":  6, "chara": "azura",     "atr": "6",  "zoen": 1},
  {"map": "nageki",  "x":   16, "y":  8, "chara": "validar",   "atr": "3",  "zoen": null},
  {"map": "nageki",  "x":   16, "y":  8, "chara": "celica",    "atr": "4",  "zoen": null},
  {"map": "nageki",  "x":   16, "y":  8, "chara": "lyn",       "atr": "4",  "zoen": 1},
  {"map": "nageki",  "x":   16, "y":  8, "chara": "corrin",    "atr": "5",  "zoen": null},
  {"map": "nageki",  "x":   16, "y":  8, "chara": "leo",       "atr": "5",  "zoen": 1},
  {"map": "nageki",  "x":   16, "y":  8, "chara": "robin",     "atr": "6",  "zoen": null},
  {"map": "nageki",  "x":   16, "y":  8, "chara": "velezark",  "atr": "6",  "zoen": 1},
  {"map": "nageki",  "x":   16, "y":  8, "chara": "darios",    "atr": "6",  "zoen": 1},
  {"map": "kamigami","x":   2,  "y":  9, "chara": "hinoka",    "atr": "3",  "zoen": null},
  {"map": "kamigami","x":   2,  "y":  9, "chara": "ceada",     "atr": "4",  "zoen": null},
  {"map": "kamigami","x":   2,  "y":  9, "chara": "takumi",    "atr": "4",  "zoen": 1},
  {"map": "kamigami","x":   2,  "y":  9, "chara": "anna",      "atr": "5",  "zoen": null},
  {"map": "kamigami","x":   2,  "y":  9, "chara": "robin",     "atr": "5",  "zoen": 1},
  {"map": "kamigami","x":   2,  "y":  9, "chara": "sakura",    "atr": "6",  "zoen": null},
  {"map": "kamigami","x":   2,  "y":  9, "chara": "niles",     "atr": "6",  "zoen": 1},
  {"map": "kamigami","x":   2,  "y":  9, "chara": "azura",     "atr": "6",  "zoen": 1},
  {"map": "kamigami","x":   9,  "y":  4, "chara": "xander",    "atr": "3",  "zoen": null},
  {"map": "kamigami","x":   9,  "y":  4, "chara": "azura",     "atr": "4",  "zoen": null},
  {"map": "kamigami","x":   9,  "y":  4, "chara": "ryoma",     "atr": "4",  "zoen": 1},
  {"map": "kamigami","x":   9,  "y":  4, "chara": "sakura",    "atr": "5",  "zoen": null},
  {"map": "kamigami","x":   9,  "y":  4, "chara": "elise",     "atr": "5",  "zoen": 1},
  {"map": "kamigami","x":   9,  "y":  4, "chara": "leo",       "atr": "6",  "zoen": null},
  {"map": "kamigami","x":   9,  "y":  4, "chara": "niles",     "atr": "6",  "zoen": 1},
  {"map": "kamigami","x":   9,  "y":  4, "chara": "owain",     "atr": "6",  "zoen": 1},
  {"map": "koori",   "x":   3,  "y":  6, "chara": "gharnef",   "atr": "3",  "zoen": null},
  {"map": "koori",   "x":   3,  "y":  6, "chara": "oboro",     "atr": "4",  "zoen": null},
  {"map": "koori",   "x":   3,  "y":  6, "chara": "azura",     "atr": "4",  "zoen": 1},
  {"map": "koori",   "x":   3,  "y":  6, "chara": "cordelia",  "atr": "5",  "zoen": null},
  {"map": "koori",   "x":   3,  "y":  6, "chara": "anna",      "atr": "5",  "zoen": 1},
  {"map": "koori",   "x":   3,  "y":  6, "chara": "takumi",    "atr": "6",  "zoen": null},
  {"map": "koori",   "x":   3,  "y":  6, "chara": "hinoka",    "atr": "6",  "zoen": 1},
  {"map": "devil",   "x":   16, "y":  8, "chara": "anna",      "atr": "3",  "zoen": null},
  {"map": "devil",   "x":   16, "y":  8, "chara": "niles",     "atr": "4",  "zoen": null},
  {"map": "devil",   "x":   16, "y":  8, "chara": "takumi",    "atr": "4",  "zoen": 1},
  {"map": "devil",   "x":   16, "y":  8, "chara": "sakura",    "atr": "5",  "zoen": null},
  {"map": "devil",   "x":   16, "y":  8, "chara": "linde",     "atr": "5",  "zoen": 1},
  {"map": "devil",   "x":   16, "y":  8, "chara": "cordelia",  "atr": "6",  "zoen": null},
  {"map": "devil",   "x":   16, "y":  8, "chara": "hinoka",    "atr": "6",  "zoen": 1},
  {"map": "devil",   "x":   16, "y":  8, "chara": "ceada",     "atr": "6",  "zoen": 1},
  {"map": "princess","x":   1,  "y":  3, "chara": "darios",    "atr": "3",  "zoen": null},
  {"map": "princess","x":   1,  "y":  3, "chara": "lyn",       "atr": "4",  "zoen": null},
  {"map": "princess","x":   1,  "y":  3, "chara": "oboro",     "atr": "4",  "zoen": 1},
  {"map": "princess","x":   1,  "y":  3, "chara": "marth",     "atr": "5",  "zoen": null},
  {"map": "princess","x":   1,  "y":  3, "chara": "linde",     "atr": "5",  "zoen": 1},
  {"map": "princess","x":   1,  "y":  3, "chara": "navarre",   "atr": "6",  "zoen": null},
  {"map": "princess","x":   1,  "y":  3, "chara": "tiki",      "atr": "6",  "zoen": 1},
  {"map": "princess","x":   1,  "y":  3, "chara": "lucina",    "atr": "6",  "zoen": 1},
  {"map": "princess","x":   16, "y":  4, "chara": "camilla",   "atr": "4",  "zoen": null},
  {"map": "princess","x":   16, "y":  4, "chara": "ceada",     "atr": "5",  "zoen": null},
  {"map": "princess","x":   16, "y":  4, "chara": "oboro",     "atr": "5",  "zoen": 1},
  {"map": "princess","x":   16, "y":  4, "chara": "hinoka",    "atr": "6",  "zoen": null},
  {"map": "princess","x":   16, "y":  4, "chara": "iago",      "atr": "6",  "zoen": 1},
  {"map": "norda",   "x":   2,  "y":  2, "chara": "gharnef",   "atr": "3",  "zoen": null},
  {"map": "norda",   "x":   2,  "y":  2, "chara": "lianna",    "atr": "4",  "zoen": null},
  {"map": "norda",   "x":   2,  "y":  2, "chara": "darios",    "atr": "4",  "zoen": 1},
  {"map": "norda",   "x":   2,  "y":  2, "chara": "linde",     "atr": "5",  "zoen": null},
  {"map": "norda",   "x":   2,  "y":  2, "chara": "iago",      "atr": "5",  "zoen": 1},
  {"map": "norda",   "x":   2,  "y":  2, "chara": "corrin",    "atr": "6",  "zoen": null},
  {"map": "norda",   "x":   2,  "y":  2, "chara": "validar",   "atr": "6",  "zoen": 1},
  {"map": "norda",   "x":   2,  "y":  2, "chara": "velezark",  "atr": "6",  "zoen": 1},
  {"map": "norda",   "x":   15, "y":  9, "chara": "validar",   "atr": "3",  "zoen": null},
  {"map": "norda",   "x":   15, "y":  9, "chara": "oboro",     "atr": "4",  "zoen": null},
  {"map": "norda",   "x":   15, "y":  9, "chara": "navarre",   "atr": "4",  "zoen": 1},
  {"map": "norda",   "x":   15, "y":  9, "chara": "owain",     "atr": "5",  "zoen": null},
  {"map": "norda",   "x":   15, "y":  9, "chara": "lissa",     "atr": "5",  "zoen": 1},
  {"map": "norda",   "x":   15, "y":  9, "chara": "lianna",    "atr": "6",  "zoen": null},
  {"map": "norda",   "x":   15, "y":  9, "chara": "lyn",       "atr": "6",  "zoen": 1},
  {"map": "seiou",   "x":   11, "y":  7, "chara": "leo",       "atr": "3",  "zoen": null},
  {"map": "seiou",   "x":   11, "y":  7, "chara": "lyn",       "atr": "4",  "zoen": null},
  {"map": "seiou",   "x":   11, "y":  7, "chara": "marth",     "atr": "4",  "zoen": 1},
  {"map": "seiou",   "x":   11, "y":  7, "chara": "olivia",    "atr": "5",  "zoen": null},
  {"map": "seiou",   "x":   11, "y":  7, "chara": "robin",     "atr": "5",  "zoen": 1},
  {"map": "seiou",   "x":   11, "y":  7, "chara": "anna",      "atr": "6",  "zoen": null},
  {"map": "seiou",   "x":   11, "y":  7, "chara": "celica",    "atr": "6",  "zoen": 1},
  {"map": "seiou",   "x":   11, "y":  7, "chara": "chrom",     "atr": "6",  "zoen": 1},
  {"map": "seiou",   "x":   12, "y":  6, "chara": "gharnef",   "atr": "3",  "zoen": null},
  {"map": "seiou",   "x":   12, "y":  6, "chara": "camilla",   "atr": "4",  "zoen": null},
  {"map": "seiou",   "x":   12, "y":  6, "chara": "olivia",    "atr": "4",  "zoen": 1},
  {"map": "seiou",   "x":   12, "y":  6, "chara": "lucina",    "atr": "5",  "zoen": null},
  {"map": "seiou",   "x":   12, "y":  6, "chara": "owain",     "atr": "5",  "zoen": 1},
  {"map": "seiou",   "x":   12, "y":  6, "chara": "lyn",       "atr": "6",  "zoen": null},
  {"map": "seiou",   "x":   12, "y":  6, "chara": "frederick", "atr": "6",  "zoen": 1},
  {"map": "caravan", "x":   16, "y":  2, "chara": "tharja",    "atr": "3",  "zoen": null},
  {"map": "caravan", "x":   16, "y":  2, "chara": "sakura",    "atr": "4",  "zoen": null},
  {"map": "caravan", "x":   16, "y":  2, "chara": "takumi",    "atr": "4",  "zoen": 1},
  {"map": "caravan", "x":   16, "y":  2, "chara": "niles",     "atr": "5",  "zoen": null},
  {"map": "caravan", "x":   16, "y":  2, "chara": "camilla",   "atr": "5",  "zoen": 1},
  {"map": "caravan", "x":   16, "y":  2, "chara": "tiki",      "atr": "6",  "zoen": null},
  {"map": "caravan", "x":   16, "y":  2, "chara": "lissa",     "atr": "6",  "zoen": 1},
  {"map": "kiaran",  "x":   3,  "y":  3, "chara": "chrom",     "atr": "s",  "zoen": 1},
  {"map": "kiaran",  "x":   4,  "y":  8, "chara": "lissa",     "atr": "s",  "zoen": 1},
  {"map": "kiaran",  "x":   6,  "y":  6, "chara": "rowan",     "atr": "s",  "zoen": 1},
  {"map": "kiaran",  "x":   15, "y":  5, "chara": "hinoka",    "atr": "s",  "zoen": 1},
  {"map": "eiyuu",   "x":   4,  "y":  4, "chara": "tiki",      "atr": "3",  "zoen": null},
  {"map": "eiyuu",   "x":   4,  "y":  4, "chara": "celica",    "atr": "4",  "zoen": null},
  {"map": "eiyuu",   "x":   4,  "y":  4, "chara": "lyn",       "atr": "4",  "zoen": 1},
  {"map": "eiyuu",   "x":   4,  "y":  4, "chara": "takumi",    "atr": "5",  "zoen": null},
  {"map": "eiyuu",   "x":   4,  "y":  4, "chara": "leo",       "atr": "5",  "zoen": 1},
  {"map": "eiyuu",   "x":   4,  "y":  4, "chara": "robin",     "atr": "6",  "zoen": null},
  {"map": "eiyuu",   "x":   4,  "y":  4, "chara": "darios",    "atr": "6",  "zoen": 1},
  {"map": "eiyuu",   "x":   4,  "y":  4, "chara": "velezark",  "atr": "6",  "zoen": 1},
  {"map": "densetu", "x":   3,  "y":  5, "chara": "frederick", "atr": "3",  "zoen": null},
  {"map": "densetu", "x":   3,  "y":  5, "chara": "celica",    "atr": "4",  "zoen": null},
  {"map": "densetu", "x":   3,  "y":  5, "chara": "ryoma",     "atr": "4",  "zoen": 1},
  {"map": "densetu", "x":   3,  "y":  5, "chara": "olivia",    "atr": "5",  "zoen": null},
  {"map": "densetu", "x":   3,  "y":  5, "chara": "iago",      "atr": "5",  "zoen": 1},
  {"map": "densetu", "x":   3,  "y":  5, "chara": "xander",    "atr": "6",  "zoen": null},
  {"map": "densetu", "x":   3,  "y":  5, "chara": "darios",    "atr": "6",  "zoen": 1},
  {"map": "densetu", "x":   3,  "y":  5, "chara": "velezark",  "atr": "6",  "zoen": 1},
  {"map": "nageki",  "x":   5,  "y":  8, "chara": "corrin",    "atr": null, "zoen": null},
  {"map": "devil",   "x":   13, "y":  6, "chara": "minerva",   "atr": null, "zoen": null},
  {"map": "devil",   "x":   13, "y":  6, "chara": "xander",    "atr": "b",  "zoen": null},
  {"map": "densetu", "x":   4,  "y":  6, "chara": "tiki",      "atr": "s",  "zoen": null},
  {"map": "densetu", "x":   4,  "y":  6, "chara": "marth",     "atr": "s",  "zoen": null},
  {"map": "densetu", "x":   4,  "y":  6, "chara": "corrin",    "atr": "s",  "zoen": null},
  {"map": "densetu", "x":   4,  "y":  6, "chara": "ceada",     "atr": "s",  "zoen": null},
  {"map": "densetu", "x":   8,  "y":  2, "chara": "xander",    "atr": "b",  "zoen": null},
  {"map": "densetu", "x":   8,  "y":  2, "chara": "iago",      "atr": null, "zoen": null},
  {"map": "densetu", "x":   8,  "y":  2, "chara": "tiki",      "atr": null, "zoen": null},
  {"map": "densetu", "x":   8,  "y":  2, "chara": "ryoma",     "atr": null, "zoen": null},
  {"map": "densetu", "x":   8,  "y":  4, "chara": "validar",   "atr": "b",  "zoen": null},
  {"map": "densetu", "x":   8,  "y":  4, "chara": "niles",     "atr": null, "zoen": null},
  {"map": "densetu", "x":   16, "y":  8, "chara": "validar",   "atr": "b",  "zoen": null},
  {"map": "densetu", "x":   16, "y":  8, "chara": "camilla",   "atr": null, "zoen": null},
  {"map": "densetu", "x":   16, "y":  8, "chara": "sakura",    "atr": null, "zoen": null},
  {"map": "seiou",   "x":   2,  "y":  7, "chara": "tiki",      "atr": null, "zoen": null},
  {"map": "seiou",   "x":   6,  "y":  8, "chara": "corrin",    "atr": null, "zoen": null},
  {"map": "seiou",   "x":   6,  "y":  8, "chara": "leo",       "atr": null, "zoen": null},
  {"map": "seiou",   "x":   6,  "y":  8, "chara": "elise",     "atr": "b",  "zoen": null},
  {"map": "seiou",   "x":   9,  "y":  1, "chara": "tiki",      "atr": "b",  "zoen": null},
  {"map": "seiou",   "x":   16, "y":  1, "chara": "hinoka",    "atr": null, "zoen": null},
  {"map": "seiou",   "x":   16, "y":  1, "chara": "lissa",     "atr": null, "zoen": null},
  {"map": "seiou",   "x":   16, "y":  1, "chara": "ryoma",     "atr": null, "zoen": null},
  {"map": "seiou",   "x":   16, "y":  1, "chara": "camilla",   "atr": "b",  "zoen": null},
  {"map": "seiou",   "x":   16, "y":  8, "chara": "owain",     "atr": "s",  "zoen": null},
  {"map": "seiou",   "x":   16, "y":  8, "chara": "takumi",    "atr": "s",  "zoen": null},
  {"map": "seiou",   "x":   16, "y":  8, "chara": "hinoka",    "atr": "s",  "zoen": null},
  {"map": "seiou",   "x":   16, "y":  8, "chara": "darios",    "atr": "s",  "zoen": null},
  {"map": "seiou",   "x":   16, "y":  8, "chara": "sakura",    "atr": "s",  "zoen": null},
  {"map": "seiou",   "x":   16, "y":  8, "chara": "xander",    "atr": "s",  "zoen": null},
  {"map": "caravan", "x":   4,  "y":  8, "chara": "tiki",      "atr": null, "zoen": null},
  {"map": "caravan", "x":   4,  "y":  8, "chara": "rowan",     "atr": null, "zoen": null},
  {"map": "caravan", "x":   4,  "y":  8, "chara": "marth",     "atr": "b",  "zoen": null},
  {"map": "caravan", "x":   11, "y":  2, "chara": "corrin",    "atr": "b",  "zoen": null},
  {"map": "caravan", "x":   11, "y":  2, "chara": "darios",    "atr": null, "zoen": null},
  {"map": "caravan", "x":   11, "y":  2, "chara": "iago",      "atr": null, "zoen": null},
  {"map": "caravan", "x":   11, "y":  2, "chara": "robin",     "atr": null, "zoen": null},
  {"map": "caravan", "x":   16, "y":  7, "chara": "ceada",     "atr": null, "zoen": 1},
  {"map": "caravan", "x":   16, "y":  7, "chara": "takumi",    "atr": null, "zoen": 1},
  {"map": "seiou",   "x":   9,  "y":  1, "chara": "tiki",      "atr": "s",  "zoen": 1},
  {"map": "seiou",   "x":   6,  "y":  8, "chara": "ceada",     "atr": null, "zoen": 1},
  {"map": "seiou",   "x":   6,  "y":  8, "chara": "tharja",    "atr": null, "zoen": 1},
  {"map": "seiou",   "x":   6,  "y":  8, "chara": "velezark",  "atr": null, "zoen": 1},
  {"map": "caravan", "x":   11, "y":  2, "chara": "iago",      "atr": "s",  "zoen": 1}
]

