[
  {"battle": "akuno",       "name": "悪の司祭ガーネフ"},
  {"battle": "bouei",       "name": "防衛戦"},
  {"battle": "caravan",     "name": "キャラバンの踊り子"},
  {"battle": "dassyutu",    "name": "脱出戦"},
  {"battle": "densetu",     "name": "伝説の継承者"},
  {"battle": "devil",       "name": "デビルマウンテン"},
  {"battle": "eiyuu",       "name": "英雄王の戦い"},
  {"battle": "gold",        "name": "ゴールドラッシュ"},
  {"battle": "gouryuu",     "name": "合流阻止戦"},
  {"battle": "haruka",      "name": "遥かなる光"},
  {"battle": "heityou",     "name": "兵長殲滅戦"},
  {"battle": "hitono",      "name": "人の心の中にあるもの"},
  {"battle": "jikan",       "name": "時間内に多くの敵を倒せ！"},
  {"battle": "kamigami",    "name": "神々の座す国"},
  {"battle": "kiaran",      "name": "キアランの公女"},
  {"battle": "kokoroni",    "name": "心に従う者たち"},
  {"battle": "koori",       "name": "氷の村"},
  {"battle": "kyougeki",    "name": "挟撃突破戦"},
  {"battle": "murabito",    "name": "村人解放戦"},
  {"battle": "murabitodef", "name": "村人を守り通せ！"},
  {"battle": "nageki",      "name": "嘆きの獣"},
  {"battle": "norda",       "name": "ノルダの市場"},
  {"battle": "princess",    "name": "プリンセス・ミネルバ"},
  {"battle": "saikai",      "name": "再開 そして・・・"},
  {"battle": "samayoi",     "name": "彷徨い揺蕩う心"},
  {"battle": "seigen",      "name": "制限時間内に敵を倒せ！"},
  {"battle": "seiou",       "name": "聖王エメリナ"},
  {"battle": "settoku",     "name": "説得戦"},
  {"battle": "shadow",      "name": "シャドー殲滅戦"},
  {"battle": "shadowrush",  "name": "シャドーラッシュ"},
  {"battle": "sonote",      "name": "その手が拓いた未来"},
  {"battle": "sonotean",    "name": "その手が拓く未来・暗夜"},
  {"battle": "sonotebya",   "name": "その手が拓く未来・白夜"},
  {"battle": "sorezore",    "name": "それぞれの想い"},
  {"battle": "toride",      "name": "砦制圧戦"},
  {"battle": "tougi",       "name": "闘技場"},
  {"battle": "unmeika",     "name": "運命か、絆か"},
  {"battle": "unmeini",     "name": "運命に抗う者"},
  {"battle": "yuugun",      "name": "友軍救出戦"}
]

